{
  "date": "2026-05-05",
  "generatedAt": "2026-05-04T17:29:07.307Z",
  "data": {
    "title": "2026년 5월 1주차 AI 카드 리포트",
    "summary": {
      "title": "가정의 달 맞춤형 소비 전략",
      "body": "5월 가정의 달을 맞아 가족 단위 외식, 여행, 교육비 지출이 급증하며 관련 특화 카드들의 활용도가 높아지고 있습니다. 특히 마일리지 적립형과 생활 밀착형 할인 카드를 조합하여 실적을 분산하는 전략이 효율적입니다. 카드사들은 연휴 기간을 겨냥한 무이자 할부 및 포인트 적립 이벤트를 강화하며 소비 심리 회복을 견인하고 있습니다.",
      "mood": "positive"
    },
    "rankings": [
      {
        "rank": 1,
        "title": "삼성카드 & MILEAGE PLATINUM (스카이패스)",
        "subtitle": "삼성카드",
        "badge": "▲5",
        "badgeType": "up",
        "highlight": "여름 휴가 준비를 위한 압도적인 항공 마일리지 적립 효율",
        "detail": "모든 가맹점에서 스카이패스 마일리지가 기본 적립되며, 백화점 및 주유 등 주요 업종에서 추가 적립 혜택을 제공합니다. 다가오는 여름 휴가 시즌을 대비해 항공권 구매를 계획 중인 사용자들에게 가장 높은 가성비를 보여줍니다.",
        "tags": [
          "마일리지",
          "여행",
          "플래티넘"
        ]
      },
      {
        "rank": 2,
        "title": "신한카드 Mr.Life",
        "subtitle": "신한카드",
        "badge": "NEW",
        "badgeType": "new",
        "highlight": "1인 가구 및 생활 밀착형 고정비 절감 최적화",
        "detail": "공과금, 통신비, 식음료 등 매달 발생하는 고정 지출에 대해 강력한 할인 혜택을 제공합니다. 5월 가정의 달 외식 물가 상승에 대응하여 생활비 방어용 카드로 새롭게 주목받고 있습니다.",
        "tags": [
          "생활비",
          "공과금",
          "1인가구"
        ]
      },
      {
        "rank": 3,
        "title": "하나카드 트래블로그 신용카드",
        "subtitle": "하나카드",
        "badge": "→유지",
        "badgeType": "same",
        "highlight": "해외 여행 및 직구 시 환전 수수료 면제 혜택",
        "detail": "해외 결제 시 수수료 면제 및 환전 우대 혜택을 통해 여행객들에게 필수 카드로 자리 잡았습니다. 최근 해외 여행 수요가 폭발적으로 증가함에 따라 꾸준한 사용률을 기록하고 있습니다.",
        "tags": [
          "해외여행",
          "환전수수료",
          "트래블"
        ]
      }
    ],
    "events": [
      {
        "issuer": "삼성카드",
        "title": "가정의 달 맞이 무이자 할부 이벤트",
        "period": "~5/31",
        "detail": "주요 가전 및 백화점 업종 최대 6개월 무이자 할부 제공"
      },
      {
        "issuer": "신한카드",
        "title": "가족 여행 경비 캐시백 프로모션",
        "period": "~5/20",
        "detail": "여행사 및 항공권 결제 시 이용 금액대별 최대 5만 원 캐시백"
      },
      {
        "issuer": "우리카드",
        "title": "쇼핑 업종 포인트 적립 강화",
        "period": "~5/15",
        "detail": "온라인 쇼핑몰 결제 시 기본 적립 외 추가 2% 포인트 적립"
      },
      {
        "issuer": "롯데카드",
        "title": "LOCA 시리즈 이용 고객 경품 추첨",
        "period": "~5/31",
        "detail": "LOCA 카드 이용 고객 대상 추첨을 통해 호텔 숙박권 증정"
      },
      {
        "issuer": "현대카드",
        "title": "M포인트 사용처 확대 이벤트",
        "period": "~5/31",
        "detail": "외식 및 문화 공연 업종에서 M포인트 50% 사용 가능"
      },
      {
        "issuer": "하나카드",
        "title": "트래블로그 해외 결제 캐시백",
        "period": "~5/31",
        "detail": "해외 현지 결제 시 이용 금액의 1% 하나머니 적립"
      }
    ],
    "comboInsight": {
      "card1": "삼성카드 & MILEAGE PLATINUM (스카이패스)",
      "card1Issuer": "삼성카드",
      "card1Benefits": [
        "항공 마일리지 적립"
      ],
      "card2": "신한카드 Mr.Life",
      "card2Issuer": "신한카드",
      "card2Benefits": [
        "생활비 할인"
      ],
      "coveragePercent": 89,
      "monthlySaving": 53200,
      "description": "마일리지 적립형 카드와 생활비 할인형 카드를 조합하여 여행과 일상 소비를 완벽하게 분리했습니다. 두 카드의 실적을 효율적으로 배분하면 월평균 5만 원 이상의 고정 비용 절감 효과를 기대할 수 있습니다."
    },
    "nextWeek": {
      "preview": "5월 중순으로 접어들며 여행 관련 소비가 정점에 달할 것으로 예상됩니다. 카드사들은 여행객을 타깃으로 한 공항 라운지 무료 이용 및 면세점 할인 혜택을 강화할 전망입니다. 또한, 6월 초 징검다리 연휴를 대비한 얼리버드 여행 상품 결제 프로모션이 활발해질 것입니다.",
      "keywords": [
        "여행",
        "공항라운지",
        "얼리버드",
        "소비패턴"
      ]
    }
  }
}