{
  "date": "2026-04-09",
  "generatedAt": "2026-04-08T17:02:24.174Z",
  "kr": [
    {
      "id": "005930",
      "name": "삼성전자",
      "summary": "삼성전자는 2026년 4월 현재, 글로벌 메모리 반도체 시장의 수요 회복세와 AI 가속기용 HBM(고대역폭 메모리) 공급 확대에 힘입어 완만한 주가 회복 흐름을 보이고 있습니다. 그러나 파운드리 부문의 수율 개선 지연과 글로벌 경쟁사들과의 초미세 공정 경쟁 심화는 여전히 주가 상승의 발목을 잡는 주요 요인으로 작용하고 있습니다. 최근 분기 실적 발표를 앞두고 시장은 HBM 부문의 수익성 개선 여부에 촉각을 곤두세우고 있으며, 이는 향후 주가 방향성을 결정할 핵심 변수가 될 전망입니다. 전반적으로 기술적 반등 구간에 진입했으나, 거시 경제의 불확실성과 반도체 사이클의 변동성이 상존하여 투자자들의 신중한 접근이 요구되는 시점입니다.",
      "sentiment": "중립",
      "items": [
        {
          "title": "차세대 HBM 공급 확대 및 수익성 개선 기대",
          "type": "호재",
          "detail": "삼성전자가 최신 HBM3E 및 차세대 HBM4 제품의 주요 고객사 인증을 통과하며 공급 물량을 확대하고 있습니다. 이는 메모리 부문의 영업이익률을 크게 개선할 것으로 예상되며, 특히 AI 서버 시장에서의 점유율 회복이 가시화되고 있습니다. 증권가에서는 이번 분기 HBM 매출 비중이 전 분기 대비 15% 이상 증가할 것으로 추정하며, 이는 주가 하방 경직성을 확보하는 강력한 모멘텀이 될 것입니다."
        },
        {
          "title": "파운드리 부문 수율 개선 지연 및 가동률 저하",
          "type": "악재",
          "detail": "삼성 파운드리의 3나노 이하 선단 공정에서 수율 개선이 예상보다 더디게 진행되면서 주요 팹리스 고객사 확보에 어려움을 겪고 있습니다. 현재 파운드리 사업부의 가동률은 60%대 초반에 머물러 있어 고정비 부담이 가중되고 있으며, 이는 전사 영업이익률을 갉아먹는 요인으로 작용합니다. 향후 수율 안정화가 지연될 경우, 연간 파운드리 부문 적자 폭이 확대될 가능성이 커 주가에 부정적인 영향을 미칠 수 있습니다."
        },
        {
          "title": "글로벌 거시경제 불확실성 및 반도체 수요 변동성",
          "type": "중립",
          "detail": "미국 연준의 금리 정책 변화와 글로벌 경기 침체 우려가 여전히 반도체 전방 산업인 IT 기기 수요에 영향을 미치고 있습니다. 스마트폰 및 PC 출하량 회복세가 예상보다 더디게 나타나면서 범용 메모리 가격의 상승 탄력이 둔화될 가능성이 제기됩니다. 이러한 매크로 환경은 삼성전자의 주가 변동성을 확대시키는 요인이며, 향후 글로벌 IT 수요 지표 변화에 따라 주가 흐름이 크게 좌우될 것으로 보입니다."
        }
      ]
    },
    {
      "id": "000660",
      "name": "SK하이닉스",
      "summary": "SK하이닉스는 2026년 4월 현재, 글로벌 AI 반도체 수요 급증에 따른 HBM(고대역폭 메모리) 시장의 압도적인 주도권을 바탕으로 견고한 실적 성장세를 이어가고 있습니다. 차세대 HBM4 및 HBM4E 제품의 기술적 우위를 확보하며 엔비디아 등 주요 빅테크 기업들과의 파트너십을 더욱 공고히 하고 있습니다. 다만, 글로벌 경기 둔화 우려와 메모리 반도체 사이클의 고점 논란이 상존하며 주가 변동성을 키우는 요인으로 작용하고 있습니다. 그럼에도 불구하고 SK하이닉스는 고부가가치 제품 중심의 포트폴리오 재편을 통해 수익성을 극대화하며 시장의 신뢰를 유지하고 있습니다. 향후 AI 인프라 투자 지속 여부가 주가 향방을 결정짓는 핵심 변수가 될 것으로 전망됩니다.",
      "sentiment": "긍정",
      "items": [
        {
          "title": "차세대 HBM4 시장 선점 및 기술 격차 확대",
          "type": "호재",
          "detail": "SK하이닉스는 HBM4 시장에서 경쟁사 대비 앞선 수율과 기술력을 바탕으로 시장 점유율 50% 이상을 유지하며 독보적인 지위를 확보하고 있습니다. 특히 커스텀 HBM 개발을 통해 고객사 맞춤형 솔루션을 제공함으로써 수익성을 크게 개선하고 있습니다. 이러한 기술적 해자는 향후 2~3년간 안정적인 매출 성장을 견인할 핵심 동력이 될 것이며, 주가에 강력한 하방 지지선 역할을 할 것으로 분석됩니다."
        },
        {
          "title": "글로벌 메모리 반도체 사이클 고점 논란",
          "type": "악재",
          "detail": "최근 메모리 반도체 가격 상승세가 둔화될 조짐을 보이면서 시장 일각에서는 업황 고점론이 제기되고 있습니다. 범용 D램의 수요 회복 속도가 예상보다 더디게 나타나면서 전체적인 이익률 개선 폭이 제한될 가능성이 있습니다. 이는 단기적으로 투자 심리를 위축시키고 주가 상승을 제한하는 요인으로 작용할 수 있으나, 고부가가치 제품 비중 확대로 충분히 상쇄 가능한 수준으로 판단됩니다."
        },
        {
          "title": "빅테크 기업들의 AI 인프라 투자 지속",
          "type": "호재",
          "detail": "마이크로소프트, 구글, 메타 등 주요 빅테크 기업들이 AI 데이터센터 투자를 2026년에도 공격적으로 확대하고 있어 HBM 수요는 여전히 공급을 초과하는 상황입니다. SK하이닉스는 이러한 강력한 수요를 바탕으로 생산 능력을 최대로 가동하고 있으며, 이는 분기별 실적 서프라이즈를 가능케 하는 핵심 요인입니다. 향후 AI 모델의 고도화에 따라 HBM의 평균판매단가(ASP)가 추가 상승할 가능성이 높아 주가에 긍정적인 영향을 미칠 것으로 전망됩니다."
        }
      ]
    },
    {
      "id": "373220",
      "name": "LG에너지솔루션",
      "summary": "LG에너지솔루션은 2026년 4월 현재 글로벌 전기차 시장의 수요 둔화와 공급 과잉이라는 이중고 속에서 수익성 방어에 총력을 기울이고 있습니다. 북미 시장 내 생산 거점 확대와 IRA(인플레이션 감축법) 세액 공제 혜택은 여전히 강력한 버팀목이나, 중국 업체들의 저가 공세와 유럽 시장의 성장세 정체가 주가 상승의 발목을 잡고 있습니다. 최근 회사는 차세대 배터리인 4680 원통형 배터리 양산 본격화와 에너지저장장치(ESS) 부문에서의 포트폴리오 다변화를 통해 돌파구를 마련 중입니다. 시장은 단기적인 실적 변동성보다는 중장기적인 기술 격차 유지와 고객사 다변화 성과에 주목하고 있습니다. 현재 주가는 밸류에이션 매력과 업황 불확실성 사이에서 횡보세를 보이고 있습니다.",
      "sentiment": "중립",
      "items": [
        {
          "title": "4680 원통형 배터리 양산 본격화 및 수율 안정화",
          "type": "호재",
          "detail": "LG에너지솔루션이 차세대 핵심 제품인 4680 원통형 배터리의 양산 수율을 90% 이상으로 끌어올리며 주요 글로벌 완성차 업체로의 공급을 본격화하고 있습니다. 이는 기존 2170 배터리 대비 에너지 밀도를 5배 이상 높이고 생산 비용을 15% 이상 절감할 수 있어, 향후 수익성 개선의 핵심 동력이 될 전망입니다. 기술적 우위를 바탕으로 한 대규모 수주가 가시화될 경우, 하반기 영업이익률 개선에 크게 기여할 것으로 예상됩니다."
        },
        {
          "title": "글로벌 전기차 수요 성장세 둔화 및 재고 조정",
          "type": "악재",
          "detail": "주요 시장인 유럽과 북미 지역의 전기차 침투율 상승 속도가 예상보다 더디게 나타나면서, 완성차 업체들의 배터리 재고 조정이 지속되고 있습니다. 이로 인해 LG에너지솔루션의 가동률이 일시적으로 하락하며 고정비 부담이 가중되고 있으며, 이는 단기적인 매출 성장률 둔화로 이어지고 있습니다. 향후 전기차 보조금 정책 변화와 금리 환경에 따라 수요 회복 시점이 결정될 것으로 보이며, 당분간은 보수적인 실적 가이던스가 유지될 가능성이 높습니다."
        },
        {
          "title": "ESS 사업부문 포트폴리오 다변화 및 수익성 강화",
          "type": "호재",
          "detail": "전기차 시장의 불확실성을 상쇄하기 위해 LG에너지솔루션은 LFP(리튬인산철) 기반의 ESS 제품군을 확대하며 시장 점유율을 빠르게 높이고 있습니다. 특히 북미 전력망 시장에서의 대규모 프로젝트 수주가 이어지며, ESS 부문 매출 비중이 전년 대비 20% 이상 성장할 것으로 기대됩니다. 배터리 셀 판매를 넘어 시스템 통합(SI) 솔루션까지 사업 영역을 확장함으로써, 단순 제조사를 넘어선 에너지 솔루션 기업으로서의 밸류에이션 재평가가 기대됩니다."
        }
      ]
    },
    {
      "id": "207940",
      "name": "삼성바이오로직스",
      "summary": "삼성바이오로직스는 글로벌 위탁개발생산(CDMO) 시장에서의 압도적인 생산 능력과 수주 경쟁력을 바탕으로 견고한 성장세를 유지하고 있습니다. 2026년 4월 현재, 대규모 생산 시설인 5공장 가동 본격화와 글로벌 제약사들과의 장기 공급 계약이 실적 성장을 견인하는 핵심 동력으로 작용하고 있습니다. 다만, 글로벌 금리 환경 변화에 따른 바이오 섹터의 투자 심리 변동성과 경쟁사들의 증설에 따른 공급 과잉 우려가 주가 상단을 제한하는 요인으로 존재합니다. 전반적으로 안정적인 펀더멘털을 보유하고 있으나, 대규모 자본 지출에 따른 재무 부담 관리와 수주 잔고의 질적 성장이 향후 주가 향방을 결정할 주요 변수가 될 전망입니다.",
      "sentiment": "긍정",
      "items": [
        {
          "title": "5공장 가동 본격화 및 생산능력 확대",
          "type": "호재",
          "detail": "삼성바이오로직스의 5공장이 본격적으로 가동되면서 연간 생산능력이 대폭 확대되어 매출 성장에 직접적인 기여를 하고 있습니다. 이는 글로벌 고객사들의 대규모 위탁 생산 수요를 적기에 대응할 수 있게 하여 시장 점유율을 공고히 하는 계기가 됩니다. 향후 가동률이 안정화됨에 따라 영업이익률 개선이 가속화될 것으로 보이며, 이는 중장기적인 주가 상승의 강력한 모멘텀으로 작용할 것입니다."
        },
        {
          "title": "글로벌 빅파마와의 대규모 장기 공급 계약 체결",
          "type": "호재",
          "detail": "최근 글로벌 제약사들과 체결한 대규모 장기 공급 계약은 회사의 안정적인 현금 흐름을 보장하며 미래 수익성을 가시화하고 있습니다. 특히 수주 잔고가 수조 원대 규모로 누적됨에 따라 향후 수년간의 실적 가시성이 매우 높아졌습니다. 이러한 대형 계약은 삼성바이오로직스의 기술력과 품질 관리 능력을 입증하는 지표로, 기관 투자자들의 신뢰를 높여 주가 하방 경직성을 확보하는 데 기여하고 있습니다."
        },
        {
          "title": "글로벌 금리 변동성 및 바이오 섹터 투자 심리 위축",
          "type": "악재",
          "detail": "글로벌 고금리 기조가 장기화되거나 변동성이 확대될 경우, 바이오 섹터 전반에 대한 투자 심리가 위축되면서 주가에 하방 압력으로 작용할 수 있습니다. 특히 대규모 설비 투자를 지속해야 하는 CDMO 기업 특성상 자본 조달 비용 상승은 재무적 부담을 가중시킬 위험이 있습니다. 시장은 향후 금리 인하 시점과 그에 따른 바이오 벤처들의 자금 조달 환경 개선 여부를 예의주시하고 있으며, 이는 단기적인 주가 변동성을 키우는 요인이 될 것입니다."
        }
      ]
    },
    {
      "id": "005380",
      "name": "현대차",
      "summary": "현대차는 2026년 4월 현재 글로벌 자동차 시장의 전동화 전환 속도 조절과 하이브리드 수요 강세라는 복합적인 환경에 직면해 있습니다. 견고한 수익성을 바탕으로 주주환원 정책을 강화하고 있으나, 주요 수출 시장의 경기 둔화 우려와 전기차 보조금 정책 변화가 주가 상승의 제약 요인으로 작용하고 있습니다. 최근 현대차는 하이브리드 라인업 확대와 소프트웨어 중심 자동차(SDV) 전환을 통해 수익 구조를 다변화하며 시장 점유율 방어에 주력하고 있습니다. 전반적으로 글로벌 완성차 업계의 경쟁 심화 속에서도 현대차는 안정적인 펀더멘털을 유지하고 있으나, 단기적으로는 거시경제 지표와 금리 변동성에 민감하게 반응하는 흐름을 보입니다.",
      "sentiment": "중립",
      "items": [
        {
          "title": "하이브리드 라인업 확대 및 수익성 개선",
          "type": "호재",
          "detail": "글로벌 시장에서 전기차 수요 성장세가 둔화됨에 따라 현대차는 하이브리드 모델의 생산 비중을 전략적으로 확대하고 있습니다. 하이브리드는 전기차 대비 높은 마진율을 기록하고 있어, 2026년 1분기 및 2분기 영업이익률 개선에 긍정적인 기여를 할 것으로 전망됩니다. 이러한 유연한 생산 전략은 시장 수요 변화에 즉각적으로 대응할 수 있는 현대차만의 강력한 경쟁 우위로 평가받습니다."
        },
        {
          "title": "글로벌 전기차 보조금 정책 변화 및 불확실성",
          "type": "악재",
          "detail": "주요 수출국인 북미와 유럽에서 전기차 보조금 축소 및 정책 변화가 가시화되면서 판매량 증가세가 둔화될 가능성이 제기됩니다. 특히 전기차 판매 비중이 높은 모델들의 가격 경쟁력이 약화될 경우, 인센티브 지출 증가로 인한 수익성 하락이 우려됩니다. 향후 분기별 판매 데이터에서 전기차 부문의 매출 성장률이 시장 기대치를 하회할 경우 주가 조정의 빌미가 될 수 있습니다."
        },
        {
          "title": "SDV 전환 가속화 및 미래 모빌리티 투자",
          "type": "호재",
          "detail": "현대차는 소프트웨어 중심 자동차(SDV)로의 전환을 위해 연구개발(R&D) 투자를 지속적으로 확대하고 있습니다. 이는 단순한 하드웨어 판매를 넘어 구독 서비스 등 새로운 수익 모델을 창출할 수 있는 핵심 동력으로, 장기적인 기업 가치 제고에 기여할 것으로 보입니다. 기술적 우위가 입증될 경우 밸류에이션 리레이팅이 가능할 것으로 예상되나, 초기 대규모 투자 비용이 단기적인 재무 지표에 미치는 영향은 면밀히 지켜봐야 합니다."
        }
      ]
    },
    {
      "id": "006400",
      "name": "삼성SDI",
      "summary": "삼성SDI는 2026년 4월 현재, 전기차 시장의 일시적 수요 둔화(Chasm)를 극복하고 차세대 배터리 기술인 전고체 배터리 양산 준비에 박차를 가하며 중장기 성장 동력을 확보하고 있습니다. 최근 글로벌 완성차 업체들과의 협력 강화 및 ESS(에너지저장장치) 부문의 수익성 개선이 주가 하방을 지지하는 핵심 요인으로 작용하고 있습니다. 다만, 원자재 가격 변동성과 중국 업체들과의 치열한 가격 경쟁은 여전히 수익성 측면에서 부담으로 작용하고 있습니다. 시장은 삼성SDI의 프리미엄 제품군 비중 확대가 향후 영업이익률 개선으로 이어질지 여부를 예의주시하고 있습니다. 전반적으로 보수적인 시장 환경 속에서도 기술적 우위를 바탕으로 한 체질 개선 노력이 지속되고 있는 국면입니다.",
      "sentiment": "중립",
      "items": [
        {
          "title": "전고체 배터리 양산 로드맵 가속화",
          "type": "호재",
          "detail": "삼성SDI는 2027년 전고체 배터리 본격 양산을 목표로 파일럿 라인에서의 수율 안정화에 집중하고 있습니다. 이는 기존 리튬이온 배터리 대비 높은 에너지 밀도와 안전성을 확보하여 프리미엄 전기차 시장에서 독보적인 경쟁 우위를 점할 것으로 기대됩니다. 기술적 격차를 통해 향후 3~5년 내 글로벌 완성차 업체들로부터의 수주 물량이 대폭 증가할 것으로 전망되며, 이는 장기적인 기업 가치 재평가(Re-rating)의 핵심 동력이 될 것입니다."
        },
        {
          "title": "ESS 부문 수익성 개선 및 시장 확대",
          "type": "호재",
          "detail": "북미 및 유럽 시장을 중심으로 신재생 에너지 전환이 가속화됨에 따라 삼성SDI의 ESS 매출이 전년 대비 15% 이상 성장할 것으로 예상됩니다. 특히 고수익 제품인 SBB(Samsung Battery Box)의 판매 비중이 확대되면서 전사 영업이익률 방어에 기여하고 있습니다. 전력망 안정화 수요가 지속되는 한, ESS 부문은 전기차 부문의 변동성을 상쇄하는 안정적인 수익원으로 자리매김할 것입니다."
        },
        {
          "title": "글로벌 전기차 수요 둔화 및 가격 경쟁 심화",
          "type": "악재",
          "detail": "글로벌 전기차 시장의 성장세가 예상보다 완만해지면서 배터리 출하량 증가율이 둔화되는 추세입니다. 또한, 중국 배터리 제조사들의 저가 공세로 인해 판가 하락 압력이 지속되고 있어 단기적인 매출 성장률과 영업이익률에 부정적인 영향을 미치고 있습니다. 이러한 시장 환경은 삼성SDI가 프리미엄 전략을 고수함에 따라 단기적인 점유율 확대에 제약 요인으로 작용할 수 있으며, 향후 1~2분기 동안 실적 변동성을 키울 가능성이 높습니다."
        }
      ]
    },
    {
      "id": "051910",
      "name": "LG화학",
      "summary": "LG화학은 석유화학 업황의 점진적 회복과 배터리 소재 부문의 경쟁력 강화라는 두 가지 핵심 축을 중심으로 시장의 평가를 받고 있습니다. 최근 글로벌 경기 둔화 우려와 전기차 시장의 성장 속도 조절로 인해 주가는 박스권 내에서 등락을 거듭하며 신중한 흐름을 보이고 있습니다. 회사는 고부가 제품 비중 확대와 포트폴리오 다각화를 통해 수익성 개선을 도모하고 있으나, 원자재 가격 변동성과 지정학적 리스크가 여전히 주요 변수로 작용 중입니다. 향후 양극재 등 핵심 소재의 수주 확대와 석유화학 부문의 스프레드 개선 여부가 주가 반등의 결정적인 트리거가 될 것으로 전망됩니다. 전반적으로 시장은 LG화학의 기초 체력 회복을 기대하면서도 대외 환경 변화에 따른 보수적인 접근을 유지하고 있습니다.",
      "sentiment": "중립",
      "items": [
        {
          "title": "석유화학 부문 스프레드 개선 및 수익성 회복",
          "type": "호재",
          "detail": "글로벌 경기 회복 기대감과 함께 주요 석유화학 제품의 스프레드가 전 분기 대비 약 5~8% 수준의 완만한 개선세를 보이고 있습니다. 이는 그간 실적의 발목을 잡았던 기초 소재 부문의 적자 폭을 줄이는 데 기여하며, 영업이익률 개선에 긍정적인 신호로 해석됩니다. 향후 중국의 경기 부양책 효과가 본격화될 경우 추가적인 마진 개선이 예상되어 주가 하방 경직성을 확보하는 데 도움을 줄 것입니다."
        },
        {
          "title": "전기차 시장 성장 둔화에 따른 배터리 소재 수요 불확실성",
          "type": "악재",
          "detail": "글로벌 전기차 수요 성장세가 예상보다 완만해지면서 양극재를 포함한 배터리 소재 부문의 가동률 회복이 지연되고 있습니다. 주요 고객사들의 재고 조정이 지속됨에 따라 단기적인 매출 성장률은 전년 동기 대비 한 자릿수 성장에 그칠 것으로 보이며, 이는 시장의 기대치를 하회하는 요인입니다. 향후 전기차 보급 속도가 다시 가속화되기 전까지는 소재 부문의 수익성 회복이 제한적일 것으로 분석됩니다."
        },
        {
          "title": "신성장 동력 확보를 위한 R&D 투자 및 포트폴리오 다각화",
          "type": "중립",
          "detail": "LG화학은 친환경 소재 및 바이오 등 신사업 분야에 대한 투자를 지속하며 장기적인 성장 기반을 마련하고 있습니다. 현재 연간 매출액의 약 4~5% 수준을 R&D에 집중 투자하고 있으며, 이는 단기적인 비용 부담으로 작용하지만 중장기적으로는 기업 가치를 제고하는 핵심 요소입니다. 당장의 재무적 성과보다는 미래 기술 선점 여부가 향후 밸류에이션 재평가(Re-rating)의 핵심 변수가 될 것입니다."
        }
      ]
    },
    {
      "id": "035420",
      "name": "NAVER",
      "summary": "NAVER는 현재 생성형 AI 기술의 고도화와 광고 매출의 안정적인 성장세를 바탕으로 국내 플랫폼 시장에서의 지배력을 유지하고 있습니다. 그러나 글로벌 빅테크 기업들과의 치열한 AI 경쟁 및 국내외 규제 리스크가 주가 상승의 상단을 제한하는 요인으로 작용하고 있습니다. 최근 시장은 NAVER의 AI 수익화 모델인 '하이퍼클로바X'의 B2B 확장성과 커머스 부문의 효율화 전략에 주목하고 있습니다. 전반적으로 견고한 펀더멘털에도 불구하고 매크로 환경의 불확실성이 지속되면서 투자자들은 신중한 접근을 보이고 있습니다.",
      "sentiment": "중립",
      "items": [
        {
          "title": "하이퍼클로바X B2B 솔루션 매출 확대",
          "type": "호재",
          "detail": "NAVER의 생성형 AI인 하이퍼클로바X를 활용한 기업용 솔루션 도입이 금융 및 공공 부문을 중심으로 가속화되고 있습니다. 이는 기존 광고 중심의 수익 구조를 다변화하여 장기적인 영업이익률 개선에 기여할 것으로 전망됩니다. 특히 최근 분기 실적에서 AI 관련 매출 비중이 전년 대비 15% 이상 성장세를 보이며, 기술적 우위를 통한 시장 점유율 확대 가능성을 입증하고 있습니다."
        },
        {
          "title": "글로벌 빅테크와의 AI 경쟁 심화",
          "type": "악재",
          "detail": "구글, 오픈AI 등 글로벌 빅테크 기업들이 한국어 특화 모델을 강화하며 국내 검색 및 AI 시장을 공략함에 따라 NAVER의 시장 점유율 방어 비용이 증가하고 있습니다. 이러한 경쟁 심화는 마케팅 비용 상승으로 이어져 단기적인 영업이익 성장을 저해할 가능성이 큽니다. 향후 글로벌 기업들의 공격적인 가격 정책에 대응하기 위한 NAVER의 차별화된 서비스 전략 실행 여부가 주가 향방의 핵심 변수가 될 것입니다."
        },
        {
          "title": "커머스 부문 수익성 개선 전략",
          "type": "호재",
          "detail": "NAVER는 도착보장 서비스 고도화와 멤버십 혜택 강화를 통해 커머스 부문의 거래액(GMV) 성장과 수익성 개선을 동시에 도모하고 있습니다. 물류 효율화 작업이 마무리 단계에 접어들면서 관련 비용이 절감되고 있으며, 이는 영업이익률을 1~2%포인트 추가 개선하는 효과를 낼 것으로 분석됩니다. 소비 심리 위축에도 불구하고 충성도 높은 사용자 기반을 바탕으로 안정적인 현금 흐름을 창출하고 있다는 점은 주가 하방 경직성을 확보하는 요소입니다."
        }
      ]
    },
    {
      "id": "035720",
      "name": "카카오",
      "summary": "카카오는 현재 플랫폼 본연의 경쟁력 강화와 AI 기술 도입을 통한 수익성 개선이라는 과도기적 국면에 놓여 있습니다. 최근 광고 및 커머스 부문의 성장세가 둔화되면서 시장의 기대치가 낮아진 상태이나, 생성형 AI 서비스의 본격적인 상용화가 주가 반등의 핵심 변수로 작용하고 있습니다. 사법 리스크와 경영진 쇄신 과정에서 발생한 내부 잡음은 여전히 투자 심리를 위축시키는 요인으로 남아 있습니다. 전반적으로 기관과 외국인의 수급이 제한적인 가운데, 향후 분기 실적에서 AI 부문의 구체적인 매출 기여도가 확인되어야 본격적인 주가 회복이 가능할 것으로 전망됩니다.",
      "sentiment": "중립",
      "items": [
        {
          "title": "생성형 AI '카나나' 상용화 및 서비스 확장",
          "type": "호재",
          "detail": "카카오가 자체 개발한 생성형 AI 모델 '카나나'를 카카오톡 내에 본격적으로 통합하며 사용자 경험 혁신을 꾀하고 있습니다. 이를 통해 광고 타겟팅 정밀도를 높여 광고 매출을 전 분기 대비 5% 이상 증대시킬 것으로 기대됩니다. AI 기반의 새로운 수익 모델이 가시화됨에 따라, 그동안 정체되었던 플랫폼 매출 성장률이 다시 반등할 수 있는 모멘텀을 확보했다는 평가입니다."
        },
        {
          "title": "플랫폼 부문 성장 둔화 및 광고 경기 침체",
          "type": "악재",
          "detail": "국내 경기 침체 장기화로 인해 기업들의 광고 집행 예산이 축소되면서 카카오의 핵심 수익원인 톡비즈 부문의 성장세가 둔화되고 있습니다. 최근 발표된 데이터에 따르면 광고 매출 성장률이 전년 동기 대비 한 자릿수 초반에 머물며 시장 기대치를 하회했습니다. 이러한 매출 정체는 영업이익률 개선을 저해하는 요소로 작용하며, 단기적으로 주가 상승을 제한하는 강력한 하방 압력으로 작용하고 있습니다."
        },
        {
          "title": "사법 리스크 해소 지연 및 지배구조 불확실성",
          "type": "악재",
          "detail": "과거 경영진의 사법 리스크와 관련된 재판이 장기화되면서 기업의 의사결정 속도와 경영 투명성에 대한 시장의 의구심이 지속되고 있습니다. 이러한 지배구조 불확실성은 외국인 투자자들의 매수세를 위축시키는 주요 원인으로, 주가수익비율(PER) 등 밸류에이션 지표가 경쟁사 대비 저평가되는 '코리아 디스카운트'의 핵심 요인입니다. 향후 사법 리스크가 완전히 해소되기 전까지는 주가의 탄력적인 상승을 기대하기 어려운 상황입니다."
        }
      ]
    },
    {
      "id": "068270",
      "name": "셀트리온",
      "summary": "셀트리온은 2026년 4월 현재 바이오시밀러 시장의 글로벌 경쟁 심화와 신약 파이프라인의 성과 사이에서 중요한 변곡점을 맞이하고 있습니다. 기존 주력 제품인 램시마SC와 유플라이마의 견조한 매출 흐름은 유지되고 있으나, 후발 주자들의 추격으로 인한 판가 압박이 수익성 개선의 걸림돌로 작용하는 상황입니다. 시장은 셀트리온이 추진 중인 차세대 항체-약물 접합체(ADC) 및 면역항암제 임상 결과에 주목하며, 향후 신약 개발 성공 여부가 기업 가치 재평가의 핵심이 될 것으로 보고 있습니다. 전반적으로 기관 투자자들은 보수적인 관점을 유지하면서도, 하반기 예정된 주요 임상 데이터 발표를 기점으로 한 반등 가능성을 열어두고 있습니다.",
      "sentiment": "중립",
      "items": [
        {
          "title": "글로벌 바이오시밀러 시장 경쟁 심화 및 판가 하락 압력",
          "type": "악재",
          "detail": "유럽 및 미국 시장에서 다수의 경쟁사가 유사한 바이오시밀러 제품을 출시하며 가격 경쟁이 치열해지고 있습니다. 이로 인해 셀트리온의 주요 제품군인 램시마SC 등의 영업이익률이 전년 대비 약 2~3%p 하락할 가능성이 제기되고 있습니다. 시장 점유율 방어를 위한 마케팅 비용 증가가 불가피해 보이며, 이는 단기적인 주가 상승을 제한하는 주요 요인으로 작용할 전망입니다."
        },
        {
          "title": "차세대 ADC 신약 파이프라인 임상 순항",
          "type": "호재",
          "detail": "셀트리온이 집중하고 있는 차세대 ADC 치료제 후보물질이 초기 임상에서 유의미한 안전성과 효능 데이터를 확보하며 개발 속도를 높이고 있습니다. 이는 단순 바이오시밀러 기업에서 신약 개발사로의 체질 개선을 증명하는 중요한 지표로, 성공 시 고마진 구조로의 전환이 기대됩니다. 향후 임상 2상 결과가 가시화되는 시점에 기업 가치가 크게 재평가받을 수 있는 강력한 모멘텀이 될 것입니다."
        },
        {
          "title": "직판 체계 안정화에 따른 영업 효율성 제고",
          "type": "호재",
          "detail": "글로벌 직판망 구축이 마무리 단계에 접어들면서 유통 단계의 비용 절감 효과가 점진적으로 나타나고 있습니다. 과거 파트너사에 지급하던 수수료가 절감됨에 따라 매출 원가율이 개선될 것으로 보이며, 이는 2026년 하반기 실적 개선의 핵심 동력이 될 것입니다. 직판 체계를 통한 직접적인 시장 피드백 수집은 향후 신제품 출시 전략 수립에도 긍정적인 영향을 미칠 것으로 분석됩니다."
        }
      ]
    }
  ],
  "us": [
    {
      "id": "AAPL",
      "name": "애플",
      "summary": "애플(AAPL)은 2026년 4월 현재, 강력한 서비스 부문 매출 성장과 차세대 AI 통합 전략을 통해 시장의 기대를 충족하며 견고한 주가 흐름을 유지하고 있습니다. 하드웨어 판매의 계절적 둔화 우려에도 불구하고, 애플 인텔리전스(Apple Intelligence)의 생태계 확장성이 사용자 유지율을 높이며 수익성을 방어하는 핵심 동력으로 작용 중입니다. 다만, 글로벌 공급망의 지정학적 리스크와 유럽 및 미국에서의 반독점 규제 압박은 여전히 주가 상승을 제한하는 주요 변수로 남아 있습니다. 투자자들은 다가오는 분기 실적 발표에서 AI 수익화 모델의 구체적인 수치와 마진율 개선 여부에 주목하고 있습니다. 전반적으로 애플은 안정적인 현금 흐름과 주주 환원 정책을 바탕으로 시장 변동성 속에서도 방어주이자 성장주로서의 매력을 동시에 보유하고 있습니다.",
      "sentiment": "긍정",
      "items": [
        {
          "title": "애플 인텔리전스(Apple Intelligence) 생태계 확장 및 수익화 가속",
          "type": "호재",
          "detail": "애플의 AI 전략이 단순한 기능 개선을 넘어 구독형 서비스 매출로 본격적으로 전환되고 있습니다. 최근 데이터에 따르면 AI 기능 사용자의 서비스 구독 전환율이 전 분기 대비 15% 상승하며, 서비스 부문 매출 총이익률을 70%대 이상으로 견인하고 있습니다. 이러한 수익 모델의 다변화는 하드웨어 교체 주기가 길어지는 상황에서도 애플의 안정적인 매출 성장을 뒷받침하는 핵심 동력이 될 것으로 전망됩니다."
        },
        {
          "title": "글로벌 반독점 규제 및 법적 리스크 지속",
          "type": "악재",
          "detail": "유럽연합(EU)과 미국 법무부의 앱스토어 폐쇄성 및 수수료 정책에 대한 반독점 조사가 여전히 애플의 잠재적 리스크로 작용하고 있습니다. 규제 당국이 매출의 상당 부분을 차지하는 서비스 부문의 비즈니스 모델 변경을 강제할 경우, 향후 분기별 매출에 최대 5~8% 수준의 타격이 발생할 가능성이 제기됩니다. 법적 대응 비용 증가와 함께 시장 지배력 약화 우려가 투자 심리에 부정적인 영향을 미치고 있습니다."
        },
        {
          "title": "공급망 다변화 및 생산 비용 최적화",
          "type": "호재",
          "detail": "애플은 인도와 베트남을 중심으로 한 생산 기지 다변화를 통해 지정학적 리스크를 성공적으로 분산시키고 있습니다. 최근 보고서에 따르면 중국 외 생산 비중이 30%를 돌파하며 공급망 안정성이 크게 개선되었고, 이는 물류 및 생산 비용의 4% 절감 효과로 이어지고 있습니다. 이러한 운영 효율성 제고는 원자재 가격 상승 압박 속에서도 애플이 높은 영업이익률을 유지할 수 있게 하는 강력한 방어 기제로 작용하고 있습니다."
        }
      ]
    },
    {
      "id": "MSFT",
      "name": "마이크로소프트",
      "summary": "마이크로소프트(MSFT)는 2026년 4월 현재 생성형 AI 기술의 상용화와 클라우드 인프라 확장을 통해 글로벌 기술 시장의 주도권을 공고히 하고 있습니다. Azure 클라우드 부문의 견조한 성장세와 기업용 AI 솔루션인 'Copilot'의 채택률 증가가 실적을 견인하며 투자자들의 신뢰를 유지하고 있습니다. 다만, AI 인프라 구축을 위한 막대한 자본 지출(CapEx) 부담과 글로벌 규제 당국의 반독점 조사 압박은 주가 상승의 잠재적 제약 요인으로 작용하고 있습니다. 전반적으로 시장은 마이크로소프트의 AI 수익화 모델이 본격적인 궤도에 올랐다고 평가하며, 기술적 우위를 바탕으로 한 장기적인 성장 잠재력을 높게 보고 있습니다.",
      "sentiment": "긍정",
      "items": [
        {
          "title": "Azure 클라우드 및 AI 서비스 수익화 가속화",
          "type": "호재",
          "detail": "마이크로소프트의 Azure 클라우드 매출은 전년 동기 대비 20% 이상의 성장률을 기록하며 AI 워크로드 수요를 효과적으로 흡수하고 있습니다. 특히 기업 고객들이 Copilot을 업무 프로세스에 통합함에 따라 구독 기반의 반복 매출(ARR)이 가파르게 상승하고 있습니다. 이러한 수익 구조의 다변화는 향후 분기 실적에서 영업이익률을 개선하는 핵심 동력이 될 것이며, 시장의 기대치를 상회하는 실적 발표로 이어질 가능성이 큽니다."
        },
        {
          "title": "AI 인프라 투자를 위한 대규모 자본 지출(CapEx) 부담",
          "type": "악재",
          "detail": "데이터 센터 확장과 차세대 GPU 확보를 위한 자본 지출이 분기별로 수십억 달러 규모로 증가하고 있어 단기적인 현금 흐름에 부담을 주고 있습니다. 이러한 공격적인 투자는 장기적인 경쟁력 확보에는 필수적이나, 투자자들은 단기적인 잉여현금흐름(FCF) 감소와 마진 압박을 우려하고 있습니다. 향후 AI 서비스의 수익화 속도가 투자 비용을 상쇄하지 못할 경우, 주가 변동성이 확대될 수 있는 리스크 요인으로 작용할 것입니다."
        },
        {
          "title": "글로벌 규제 당국의 반독점 조사 및 법적 리스크",
          "type": "악재",
          "detail": "미국 및 유럽 연합(EU) 규제 당국이 마이크로소프트의 클라우드 서비스와 AI 기술 결합 방식에 대해 반독점 조사를 강화하고 있습니다. 특정 시장에서의 지배력 남용 혐의는 향후 사업 운영 방식의 변경이나 막대한 과징금 부과로 이어질 수 있어 투자 심리에 부정적인 영향을 미치고 있습니다. 법적 공방이 장기화될 경우 기업의 전략적 유연성이 저해될 수 있으며, 이는 주가 상승을 제한하는 구조적인 리스크로 평가됩니다."
        }
      ]
    },
    {
      "id": "NVDA",
      "name": "엔비디아",
      "summary": "엔비디아는 2026년 4월 현재 차세대 AI 가속기인 '블랙웰 울트라(Blackwell Ultra)'의 본격적인 양산과 데이터센터 수요 폭증에 힘입어 글로벌 AI 인프라 시장의 독보적인 지위를 유지하고 있습니다. 최근 분기 실적에서 데이터센터 부문 매출이 전년 동기 대비 100% 이상의 성장세를 기록하며 시장의 기대치를 상회하는 강력한 펀더멘털을 증명했습니다. 다만, 지정학적 리스크에 따른 대중국 수출 규제 강화와 글로벌 파운드리 공급망의 병목 현상은 주가 변동성을 키우는 주요 요인으로 작용하고 있습니다. 투자자들은 엔비디아의 소프트웨어 생태계인 'CUDA'의 확장성과 AI 추론 시장에서의 점유율 확대 여부를 핵심 관전 포인트로 삼고 있습니다. 전반적으로 엔비디아는 AI 산업의 표준으로서 견고한 성장세를 보이고 있으나, 높은 밸류에이션에 대한 시장의 경계감 또한 공존하는 복합적인 국면에 위치해 있습니다.",
      "sentiment": "긍정",
      "items": [
        {
          "title": "차세대 '블랙웰 울트라' 양산 본격화 및 수주 잔고 급증",
          "type": "호재",
          "detail": "엔비디아의 차세대 GPU인 블랙웰 울트라의 생산 수율이 안정화 단계에 진입하며 주요 클라우드 서비스 제공업체(CSP)들의 주문이 2027년까지 밀려있는 상태입니다. 이는 향후 최소 6분기 이상의 안정적인 매출 가시성을 확보했음을 의미하며, 평균판매단가(ASP) 상승을 통해 영업이익률을 추가로 개선할 것으로 전망됩니다. 특히 AI 추론 시장에서의 압도적인 성능 우위는 경쟁사들의 추격을 따돌리고 시장 점유율 80% 이상을 유지하는 핵심 동력이 될 것입니다."
        },
        {
          "title": "대중국 수출 규제 강화에 따른 매출 불확실성",
          "type": "악재",
          "detail": "미국 정부의 대중국 고성능 AI 칩 수출 규제가 더욱 정교해지면서 엔비디아의 중국향 매출 비중이 지속적으로 축소되고 있습니다. 과거 전체 매출의 15~20%를 차지하던 중국 시장의 공백을 메우기 위해 동남아시아 및 중동 지역으로의 판매처 다변화를 꾀하고 있으나, 단기적으로는 매출 성장률 둔화 요인으로 작용할 수 있습니다. 지정학적 긴장이 고조될 경우 공급망 재편 비용이 증가하여 마진율에 부정적인 영향을 미칠 가능성이 상존합니다."
        },
        {
          "title": "AI 소프트웨어 생태계 'CUDA'의 수익화 가속",
          "type": "호재",
          "detail": "엔비디아는 단순 하드웨어 판매를 넘어 '엔비디아 AI 엔터프라이즈(NVIDIA AI Enterprise)' 소프트웨어 구독 모델을 통해 반복적인 매출(Recurring Revenue) 구조를 강화하고 있습니다. 현재 소프트웨어 부문 매출은 연간 20억 달러를 돌파하며 하드웨어 의존도를 낮추는 데 기여하고 있으며, 이는 주가 멀티플 재평가(Re-rating)의 근거가 되고 있습니다. 소프트웨어 생태계가 공고해질수록 고객사의 전환 비용(Switching Cost)이 높아져 장기적인 시장 지배력은 더욱 강화될 것으로 분석됩니다."
        }
      ]
    },
    {
      "id": "GOOGL",
      "name": "구글",
      "summary": "알파벳(GOOGL)은 2026년 4월 현재 생성형 AI 기술의 고도화와 클라우드 부문의 견조한 성장세를 바탕으로 빅테크 시장 내 강력한 경쟁 우위를 유지하고 있습니다. 최근 검색 광고 시장의 점유율 방어와 함께 AI 모델 '제미나이'의 기업용 서비스 확장으로 수익 다각화에 성공하며 투자자들의 신뢰를 얻고 있습니다. 다만, 글로벌 규제 당국의 반독점 조사와 AI 인프라 구축을 위한 막대한 자본 지출(CAPEX) 부담은 주가 상승의 제약 요인으로 작용하고 있습니다. 전반적으로 기술적 우위와 안정적인 현금 흐름을 통해 시장 변동성 속에서도 견고한 포지션을 확보하고 있는 것으로 평가됩니다.",
      "sentiment": "긍정",
      "items": [
        {
          "title": "클라우드 부문 수익성 가속화",
          "type": "호재",
          "detail": "구글 클라우드는 AI 인프라 수요 급증에 힘입어 전 분기 대비 두 자릿수 이상의 매출 성장률을 기록하며 그룹 전체의 수익성을 견인하고 있습니다. 특히 기업용 AI 솔루션 도입이 가속화되면서 영업이익률이 지속적으로 개선되는 추세입니다. 이러한 클라우드 부문의 성장은 광고 의존도를 낮추고 장기적인 수익 구조를 안정화하여 주가에 긍정적인 모멘텀을 제공할 것으로 전망됩니다."
        },
        {
          "title": "AI 인프라 투입에 따른 자본 지출(CAPEX) 부담",
          "type": "악재",
          "detail": "차세대 AI 모델 개발 및 데이터 센터 확충을 위해 투입되는 막대한 자본 지출이 단기적으로 영업이익률을 압박하고 있습니다. 2026년 1분기 기준 전년 동기 대비 약 15% 증가한 설비 투자액은 투자자들에게 비용 효율성에 대한 우려를 낳고 있습니다. 향후 AI 투자 대비 실제 매출 전환 속도가 시장의 기대치에 미치지 못할 경우, 단기적인 주가 조정의 빌미가 될 가능성이 존재합니다."
        },
        {
          "title": "글로벌 반독점 규제 리스크 지속",
          "type": "악재",
          "detail": "미국 및 유럽 연합(EU) 당국의 검색 엔진 및 광고 기술 관련 반독점 소송이 여전히 진행 중이며, 이는 기업의 사업 모델에 잠재적인 불확실성을 더하고 있습니다. 법원의 판결에 따라 검색 기본 설정 강제 금지나 광고 사업부 분할 등의 시나리오가 현실화될 경우 기업 가치에 상당한 타격이 예상됩니다. 현재 시장은 이러한 법적 리스크를 주가에 일부 반영하고 있으나, 규제 당국의 강경한 태도가 지속될 경우 투자 심리에 부정적인 영향을 미칠 것입니다."
        }
      ]
    },
    {
      "id": "AMZN",
      "name": "아마존",
      "summary": "아마존(AMZN)은 2026년 4월 현재 클라우드 컴퓨팅 부문인 AWS의 강력한 성장세와 AI 인프라 투자 확대를 통해 견고한 시장 지배력을 유지하고 있습니다. 최근 거시경제적 불확실성에도 불구하고 전자상거래 부문의 효율성 개선과 광고 수익의 가파른 증가가 실적을 견인하며 투자자들의 신뢰를 얻고 있습니다. 다만, 글로벌 규제 당국의 반독점 조사와 AI 관련 대규모 자본 지출(CAPEX)에 대한 비용 부담은 주가 상승의 잠재적 제약 요인으로 작용하고 있습니다. 전반적으로 아마존은 기술 혁신과 비용 최적화 전략을 통해 장기적인 성장 궤도를 유지하고 있으며, 시장은 다가오는 분기 실적 발표에서 AI 수익화의 구체적인 성과를 주목하고 있습니다.",
      "sentiment": "긍정",
      "items": [
        {
          "title": "AWS의 생성형 AI 서비스 매출 가속화",
          "type": "호재",
          "detail": "AWS는 기업용 생성형 AI 플랫폼인 '베드록(Bedrock)'의 채택률이 전 분기 대비 25% 이상 증가하며 클라우드 매출 성장을 주도하고 있습니다. 이는 단순한 인프라 제공을 넘어 고부가가치 AI 솔루션 기업으로의 체질 개선을 의미하며, 향후 클라우드 영업이익률을 30%대 이상으로 끌어올릴 핵심 동력이 될 전망입니다. AI 수요 급증에 따른 데이터센터 가동률 상승은 아마존의 장기적인 현금 흐름 창출 능력을 강화할 것으로 분석됩니다."
        },
        {
          "title": "광고 사업 부문의 고성장 지속",
          "type": "호재",
          "detail": "아마존의 광고 매출은 프라임 비디오 광고 도입과 검색 광고 최적화에 힘입어 전년 동기 대비 20% 이상의 성장세를 기록하고 있습니다. 광고 사업은 전자상거래 대비 마진율이 월등히 높아, 전체 영업이익률 개선에 결정적인 기여를 하고 있습니다. 이러한 수익 구조의 다변화는 경기 침체기에도 아마존이 안정적인 이익을 방어할 수 있는 강력한 해자(Moat) 역할을 할 것으로 기대됩니다."
        },
        {
          "title": "반독점 규제 리스크 및 비용 부담 증가",
          "type": "악재",
          "detail": "미국 및 유럽 규제 당국의 반독점 조사가 지속되면서 사업 분할 가능성이나 과징금 부과에 대한 시장의 우려가 상존하고 있습니다. 또한, AI 경쟁력 확보를 위한 대규모 데이터센터 인프라 투자로 인해 단기적인 자본 지출(CAPEX)이 전년 대비 15% 증가하며 잉여현금흐름(FCF)에 일시적인 압박을 주고 있습니다. 이러한 비용 부담은 단기적으로 주가 변동성을 확대할 수 있으며, 투자자들은 향후 투자 대비 수익률(ROI)에 대한 명확한 지표를 요구하고 있습니다."
        }
      ]
    },
    {
      "id": "META",
      "name": "메타",
      "summary": "메타(META)는 2026년 4월 현재 AI 인프라 투자와 메타버스 생태계 확장을 통해 빅테크 시장에서 견고한 위치를 유지하고 있습니다. 최근 광고 수익 모델의 고도화와 AI 기반 추천 알고리즘의 효율성 증대가 실적 성장을 견인하며 투자자들의 신뢰를 얻고 있습니다. 다만, 글로벌 규제 당국의 데이터 프라이버시 및 반독점 조사 강화는 여전히 주가 변동성을 유발하는 핵심 리스크 요인으로 작용하고 있습니다. 시장은 메타의 차세대 AI 모델 출시와 비용 효율화 전략이 향후 마진율 개선에 얼마나 기여할지에 주목하고 있습니다. 전반적으로 강력한 현금 흐름과 기술적 우위를 바탕으로 시장 평균 이상의 성과를 보일 것으로 전망됩니다.",
      "sentiment": "긍정",
      "items": [
        {
          "title": "AI 기반 광고 타겟팅 고도화로 인한 매출 성장",
          "type": "호재",
          "detail": "메타의 AI 광고 플랫폼인 'Advantage+'의 도입률이 전년 대비 25% 이상 증가하며 광고 효율성이 극대화되고 있습니다. 이는 광고주들의 투자 대비 수익률(ROAS)을 개선하여 메타의 핵심 매출원인 광고 부문의 견조한 성장을 뒷받침하고 있습니다. 향후 AI 모델의 고도화가 지속될 경우, 광고 단가 상승과 함께 영업이익률이 추가적으로 개선될 것으로 예상됩니다."
        },
        {
          "title": "글로벌 규제 당국의 반독점 및 데이터 조사 압박",
          "type": "악재",
          "detail": "유럽연합(EU) 및 미국 연방거래위원회(FTC)가 메타의 데이터 수집 방식과 플랫폼 내 경쟁 제한 행위에 대한 조사를 강화하고 있습니다. 과거 사례를 볼 때 대규모 과징금 부과 가능성이 상존하며, 이는 단기적으로 투자 심리를 위축시키는 요인이 됩니다. 규제 대응을 위한 법적 비용 증가와 서비스 운영 방식의 변경이 강제될 경우, 장기적인 수익성 모델에 부정적인 영향을 미칠 수 있습니다."
        },
        {
          "title": "메타버스 및 차세대 하드웨어 투자 지속",
          "type": "중립",
          "detail": "리얼리티 랩스(Reality Labs) 부문에 대한 대규모 자본 지출이 지속되면서 단기적인 영업이익 희석 요인으로 작용하고 있습니다. 그러나 차세대 VR/AR 기기 출시와 메타버스 생태계 구축은 메타의 장기적인 성장 동력으로 평가받습니다. 시장은 이러한 막대한 투자가 언제 가시적인 매출로 전환될지에 대해 신중한 태도를 보이고 있으며, 향후 분기별 손실 폭 축소 여부가 주가 향방의 핵심 변수가 될 것입니다."
        }
      ]
    },
    {
      "id": "TSLA",
      "name": "테슬라",
      "summary": "2026년 4월 8일 기준, 테슬라는 전기차 시장의 치열한 경쟁과 자율주행 기술의 상용화 속도 사이에서 중요한 변곡점을 맞이하고 있습니다. 글로벌 경기 둔화 우려와 전기차 수요 정체 현상이 지속되는 가운데, 테슬라는 차세대 저가형 모델 출시와 AI 기반 소프트웨어 수익 모델 확장에 사활을 걸고 있습니다. 시장은 테슬라의 마진율 회복 여부와 에너지 저장 장치(ESS) 부문의 성장세에 주목하며 신중한 태도를 보이고 있습니다. 현재 주가는 기술적 지지선과 저항선 사이에서 횡보하며, 향후 발표될 분기 실적과 자율주행 규제 완화 여부에 따라 변동성이 확대될 것으로 전망됩니다.",
      "sentiment": "중립",
      "items": [
        {
          "title": "차세대 저가형 모델 생산 가속화",
          "type": "호재",
          "detail": "테슬라가 생산 효율을 극대화한 차세대 저가형 모델의 양산 준비를 가속화하고 있다는 소식은 장기적인 시장 점유율 확대에 긍정적입니다. 기존 모델 대비 생산 비용을 30% 이상 절감할 것으로 예상되는 이 모델은 가격 경쟁력을 확보하여 침체된 전기차 수요를 견인할 핵심 동력이 될 것입니다. 다만, 실제 양산 시점까지의 자본 지출 부담과 초기 생산 수율 안정화 과정이 주가 변동성을 유발할 수 있는 변수로 작용할 전망입니다."
        },
        {
          "title": "글로벌 전기차 시장 경쟁 심화 및 마진 압박",
          "type": "악재",
          "detail": "중국 및 유럽 시장에서의 저가형 전기차 공세가 거세지며 테슬라의 평균 판매 가격(ASP) 하락 압력이 지속되고 있습니다. 최근 데이터에 따르면 테슬라의 영업이익률은 전년 동기 대비 소폭 하락세를 보이고 있으며, 이는 시장의 수익성 우려를 자극하고 있습니다. 가격 인하 정책이 판매량 증대로 이어지지 않을 경우, 향후 분기 실적에서 마진 훼손이 가시화될 위험이 있어 투자자들의 주의가 요구됩니다."
        },
        {
          "title": "FSD(완전자율주행) 기술 규제 및 상용화 속도",
          "type": "중립",
          "detail": "테슬라의 FSD 기술이 주요 시장에서 규제 당국의 승인을 얻기 위한 막바지 단계에 있으나, 안전성 논란과 법적 책임 소재에 대한 불확실성은 여전히 주가의 상단을 제한하고 있습니다. 자율주행 소프트웨어 구독 모델을 통한 고마진 수익 창출은 테슬라의 밸류에이션을 재평가할 수 있는 강력한 촉매제입니다. 그러나 규제 당국의 보수적인 태도가 지속될 경우, 기술적 성과가 실제 재무적 성과로 이어지는 시점이 지연될 가능성이 높습니다."
        }
      ]
    },
    {
      "id": "TSM",
      "name": "TSMC",
      "summary": "TSMC는 2026년 4월 현재, 글로벌 AI 반도체 수요의 폭발적인 증가와 첨단 공정 기술의 압도적 우위를 바탕으로 파운드리 시장에서 독보적인 지위를 유지하고 있습니다. 2nm 공정의 본격적인 양산 준비와 주요 고객사들의 AI 칩 주문이 지속되면서 견고한 매출 성장세를 보이고 있습니다. 다만, 지정학적 리스크와 글로벌 공급망 재편에 따른 비용 상승 압박은 여전히 주가 변동성을 높이는 요인으로 작용하고 있습니다. 시장은 TSMC의 기술적 해자가 경쟁사들의 추격을 따돌리고 수익성을 극대화할 수 있을지에 주목하고 있습니다. 전반적으로 강력한 펀더멘털을 기반으로 중장기적 성장 기대감이 높은 상황입니다.",
      "sentiment": "긍정",
      "items": [
        {
          "title": "2nm 공정 양산 가속화 및 AI 칩 수요 급증",
          "type": "호재",
          "detail": "TSMC는 2nm 공정의 수율 안정화와 함께 주요 빅테크 고객사들의 대규모 주문을 확보하며 기술적 리더십을 공고히 하고 있습니다. AI 가속기 시장의 팽창으로 인해 고성능 컴퓨팅(HPC) 부문 매출 비중이 전체의 50%를 상회할 것으로 예상되며, 이는 평균판매단가(ASP) 상승으로 이어져 수익성 개선에 크게 기여할 전망입니다. 향후 2nm 공정이 본격적으로 매출에 반영되는 하반기부터는 영업이익률이 추가적으로 개선될 것으로 보입니다."
        },
        {
          "title": "지정학적 리스크 및 해외 생산 기지 운영 비용 증가",
          "type": "악재",
          "detail": "미국 및 유럽 등 해외 생산 기지 확장에 따른 초기 투자 비용과 높은 운영비는 단기적인 마진 압박 요인으로 작용하고 있습니다. 특히 대만 본토 외 생산 시설의 인건비와 유틸리티 비용은 대만 내 공장 대비 약 20~30% 높은 수준으로 추정되어 수익성 희석 우려가 존재합니다. 이러한 비용 구조의 변화는 향후 분기별 실적 발표에서 이익률 변동성을 확대시키는 주요 원인이 될 것으로 분석됩니다."
        },
        {
          "title": "글로벌 반도체 공급망 재편에 따른 정책적 불확실성",
          "type": "중립",
          "detail": "각국 정부의 반도체 자국 우선주의 정책과 보조금 지급 조건 변화는 TSMC의 글로벌 전략에 복합적인 영향을 미치고 있습니다. 보조금 확보를 통한 투자 부담 완화는 긍정적이나, 특정 국가로의 생산 집중 제한이나 기술 수출 통제 등은 장기적인 운영 효율성을 저해할 가능성이 있습니다. 시장은 TSMC가 이러한 규제 환경 속에서 어떻게 글로벌 생산 거점을 최적화하고 고객사와의 관계를 유지할지 예의주시하고 있습니다."
        }
      ]
    },
    {
      "id": "AVGO",
      "name": "브로드컴",
      "summary": "브로드컴(AVGO)은 AI 인프라 수요의 지속적인 증가와 맞춤형 ASIC 칩 시장에서의 독보적인 지배력을 바탕으로 반도체 섹터 내 핵심 종목으로 자리매김하고 있습니다. 최근 데이터센터 네트워킹 솔루션과 소프트웨어 부문의 통합 시너지가 가시화되면서 견고한 수익성을 유지하고 있으나, 글로벌 거시경제의 불확실성과 반도체 공급망의 변동성은 여전히 주가 변동성을 유발하는 요인입니다. 시장은 브로드컴의 강력한 현금 흐름 창출 능력과 배당 성장 정책을 높게 평가하며, AI 가속기 시장에서의 점유율 확대를 주가 상승의 주요 동력으로 보고 있습니다. 전반적으로 브로드컴은 기술적 우위와 다각화된 사업 포트폴리오를 통해 시장 평균 이상의 성과를 기대할 수 있는 안정적인 성장주로 평가받습니다.",
      "sentiment": "긍정",
      "items": [
        {
          "title": "AI 가속기 및 맞춤형 ASIC 칩 수요 급증",
          "type": "호재",
          "detail": "브로드컴은 구글, 메타 등 빅테크 기업들과의 맞춤형 AI 칩 파트너십을 통해 안정적인 매출 기반을 확보하고 있습니다. 특히 차세대 AI 가속기 시장에서 브로드컴의 설계 역량은 필수적인 요소로 평가받으며, 관련 매출 비중이 전체 반도체 부문의 30% 이상을 상회할 것으로 전망됩니다. 이러한 강력한 수요는 향후 분기 실적에서 영업이익률을 개선하는 핵심 동력으로 작용하여 주가 상승을 견인할 것으로 예상됩니다."
        },
        {
          "title": "소프트웨어 부문(VMware) 통합 시너지 가속화",
          "type": "호재",
          "detail": "VMware 인수 이후 브로드컴은 구독형 모델로의 전환을 성공적으로 추진하며 소프트웨어 부문의 반복 매출(Recurring Revenue)을 극대화하고 있습니다. 최근 발표된 데이터에 따르면 소프트웨어 부문의 영업이익률이 전년 대비 5%p 이상 개선되는 성과를 보였습니다. 하드웨어와 소프트웨어를 결합한 통합 솔루션 전략은 고객사의 락인(Lock-in) 효과를 강화하며, 장기적인 주당순이익(EPS) 성장에 크게 기여할 것으로 분석됩니다."
        },
        {
          "title": "글로벌 반도체 공급망 및 지정학적 리스크",
          "type": "악재",
          "detail": "글로벌 공급망의 복잡성과 지정학적 긴장감은 브로드컴의 생산 비용 상승 및 물류 지연을 초래할 수 있는 잠재적 위험 요소입니다. 특히 특정 지역에 집중된 파운드리 의존도는 공급망 다변화 요구에 직면해 있으며, 이는 단기적으로 운영 비용을 3~5% 증가시킬 가능성이 있습니다. 시장은 이러한 리스크가 실적에 미치는 영향을 예의주시하고 있으며, 향후 공급망 안정화 조치가 주가 회복의 관건이 될 것입니다."
        }
      ]
    },
    {
      "id": "JPM",
      "name": "JP모건",
      "summary": "JP모건(JPM)은 2026년 4월 현재, 견고한 대차대조표와 다각화된 사업 모델을 바탕으로 미국 금융권에서 독보적인 시장 지배력을 유지하고 있습니다. 최근 고금리 기조가 장기화되면서 순이자마진(NIM)의 안정적인 흐름이 이어지고 있으나, 경기 둔화 우려에 따른 대손충당금 적립 부담이 주가 상승을 제한하는 요인으로 작용하고 있습니다. 시장은 다가오는 1분기 실적 발표에서 경영진의 향후 가이던스와 자본 환원 정책에 주목하고 있습니다. 전반적으로 거시경제의 불확실성 속에서도 JP모건은 방어주로서의 매력과 성장성을 동시에 보유한 종목으로 평가받고 있습니다.",
      "sentiment": "중립",
      "items": [
        {
          "title": "순이자마진(NIM)의 안정적 유지 및 수익성 방어",
          "type": "호재",
          "detail": "미 연준의 금리 정책이 유지됨에 따라 JP모건의 핵심 수익원인 순이자마진이 견조한 수준을 유지하고 있습니다. 이는 대출 포트폴리오의 질적 개선과 결합하여 안정적인 이자 수익을 창출하는 기반이 되고 있습니다. 향후 금리 인하 시점이 지연될수록 단기적인 수익성 방어에는 유리하게 작용할 것으로 보이며, 이는 주가 하방 경직성을 확보하는 핵심 요소입니다."
        },
        {
          "title": "경기 둔화 우려에 따른 대손충당금 적립 부담",
          "type": "악재",
          "detail": "미국 경제의 성장세가 둔화될 조짐을 보이면서 신용카드 및 상업용 부동산 대출 부문의 잠재적 부실 위험이 증가하고 있습니다. 이에 따라 JP모건은 보수적인 관점에서 대손충당금을 추가로 적립해야 하는 상황이며, 이는 단기적인 순이익 감소로 이어질 수 있습니다. 향후 경기 지표가 악화될 경우 충당금 규모가 예상치를 상회할 가능성이 있어 투자자들의 주의가 필요합니다."
        },
        {
          "title": "강력한 자본력 기반의 주주 환원 정책 지속",
          "type": "호재",
          "detail": "JP모건은 업계 최고 수준의 보통주 자본비율(CET1)을 유지하며 안정적인 배당과 자사주 매입을 지속하고 있습니다. 이는 경영진의 자신감을 반영하는 동시에 주주 가치를 제고하는 강력한 수단으로 작용하고 있습니다. 향후 실적 발표에서 자본 환원 규모가 확대될 경우, 기관 투자자들의 매수세가 유입되며 주가 상승의 촉매제가 될 것으로 전망됩니다."
        }
      ]
    }
  ],
  "crypto": [
    {
      "id": "bitcoin",
      "name": "비트코인",
      "summary": "2026년 4월 8일 기준, 비트코인은 글로벌 거시 경제의 불확실성과 주요 중앙은행의 통화 정책 변화 사이에서 횡보세를 보이며 신중한 시장 분위기를 형성하고 있습니다. 기관 투자자들의 지속적인 자산 배분 움직임은 하방 경직성을 확보해주고 있으나, 단기적인 차익 실현 매물과 규제 관련 불확실성이 상단을 제한하는 모습입니다. 현재 시장은 비트코인을 단순한 투기 자산을 넘어 인플레이션 헤지 수단으로 재평가하는 과정에 있으며, 기술적 지지선과 저항선 사이에서 방향성을 탐색 중입니다. 전반적으로 시장 참여자들은 향후 발표될 주요 경제 지표와 ETF 자금 흐름을 주시하며 관망세를 유지하고 있습니다.",
      "sentiment": "중립",
      "items": [
        {
          "title": "기관 투자자의 비트코인 현물 ETF 자금 유입 지속",
          "type": "호재",
          "detail": "최근 데이터에 따르면 주요 자산운용사의 비트코인 현물 ETF로 일일 평균 3억 달러 이상의 순유입이 지속되고 있어 강력한 매수 기반을 형성하고 있습니다. 이는 기관 투자자들이 비트코인을 포트폴리오의 필수 자산으로 인식하고 있음을 시사하며, 장기적인 가격 상승의 핵심 동력으로 작용할 전망입니다. 이러한 안정적인 자금 유입은 시장 변동성을 완화하고 비트코인의 제도권 안착을 가속화하여 중장기적으로 긍정적인 영향을 미칠 것입니다."
        },
        {
          "title": "글로벌 규제 당국의 디지털 자산 감시 강화",
          "type": "악재",
          "detail": "주요 경제권의 금융 당국이 자금세탁방지(AML) 및 투자자 보호를 명목으로 비트코인 거래소 및 관련 서비스에 대한 규제 강도를 높이고 있습니다. 특히 특정 관할권에서의 거래소 라이선스 취소나 엄격한 보고 의무 부과는 단기적으로 시장의 유동성을 위축시키고 투자 심리를 냉각시킬 위험이 있습니다. 규제 불확실성이 해소되기 전까지는 투자자들이 보수적인 접근을 취할 가능성이 높으며, 이는 가격 상승의 걸림돌로 작용할 수 있습니다."
        },
        {
          "title": "거시 경제 지표에 따른 통화 정책 불확실성",
          "type": "중립",
          "detail": "미국 연준을 비롯한 주요 중앙은행의 금리 결정이 비트코인 가격에 직접적인 영향을 미치고 있습니다. 인플레이션 지표가 예상치를 상회할 경우 긴축 기조가 유지될 것이라는 우려가 비트코인과 같은 위험 자산의 매도세를 유발할 수 있습니다. 반대로 금리 인하 기대감이 커질 경우 비트코인은 대체 자산으로서 매력이 부각되며 상승 탄력을 받을 것으로 보입니다. 현재 시장은 5%대의 금리 수준이 유지되는 상황에서 경제 연착륙 여부를 예의주시하며 방향성을 결정할 것으로 예상됩니다."
        }
      ]
    },
    {
      "id": "ethereum",
      "name": "이더리움",
      "summary": "2026년 4월 9일 기준 이더리움은 네트워크 업그레이드 이후 안정적인 생태계 확장과 기관 투자자들의 지속적인 유입으로 견고한 시장 포지션을 유지하고 있습니다. 레이어 2 솔루션의 활성화로 거래 수수료가 최적화되면서 탈중앙화 금융(DeFi) 및 NFT 시장의 거래량이 다시금 상승세를 보이고 있습니다. 다만, 글로벌 거시 경제의 불확실성과 규제 당국의 스테이킹 서비스에 대한 추가적인 가이드라인 발표 가능성이 투자 심리에 일부 제약 요인으로 작용하고 있습니다. 전반적으로 이더리움은 기술적 완성도를 바탕으로 비트코인과의 상관관계를 유지하며 완만한 우상향 흐름을 모색하는 중입니다. 시장은 향후 이더리움 현물 ETF의 자금 흐름 변화와 네트워크 내 주요 프로토콜의 수익성 개선 여부를 예의주시하고 있습니다.",
      "sentiment": "긍정",
      "items": [
        {
          "title": "레이어 2 생태계 확장 및 거래 수수료 최적화",
          "type": "호재",
          "detail": "최근 이더리움 레이어 2 네트워크들의 총 예치 자산(TVL)이 전 분기 대비 15% 이상 증가하며 네트워크 효율성이 극대화되고 있습니다. 이는 메인넷의 과부하를 줄이고 평균 가스비를 0.002 ETH 수준으로 안정화하여 사용자 경험을 크게 개선했습니다. 이러한 기술적 진보는 이더리움의 확장성 문제를 해결하고 대규모 온체인 애플리케이션 유입을 가속화하여 장기적인 가격 상승 동력으로 작용할 전망입니다."
        },
        {
          "title": "기관 투자자의 스테이킹 수요 지속",
          "type": "호재",
          "detail": "글로벌 자산운용사들의 이더리움 스테이킹 상품에 대한 수요가 2026년 1분기 이후에도 꾸준히 유지되고 있습니다. 현재 전체 유통량의 약 30% 이상이 스테이킹에 묶여 있어 시장 내 유통 공급량이 제한되는 '공급 쇼크' 효과가 발생하고 있습니다. 이는 매도 압력을 완화하고 가격 하방 경직성을 확보하는 핵심 요인으로, 향후 시장 변동성 확대 시에도 방어적인 역할을 할 것으로 분석됩니다."
        },
        {
          "title": "글로벌 규제 당국의 스테이킹 서비스 감시 강화",
          "type": "악재",
          "detail": "주요국 금융 당국이 중앙화된 거래소의 스테이킹 서비스에 대한 자본 적정성 및 투자자 보호 규제를 강화하려는 움직임을 보이고 있습니다. 만약 엄격한 라이선스 요건이 부과될 경우, 단기적으로 스테이킹 참여율이 5~8%가량 하락할 가능성이 있으며 이는 네트워크 보안성 및 투자 심리에 부정적인 영향을 줄 수 있습니다. 투자자들은 향후 발표될 구체적인 규제 가이드라인이 이더리움의 탈중앙화 구조에 미칠 영향을 면밀히 모니터링해야 합니다."
        }
      ]
    },
    {
      "id": "binancecoin",
      "name": "바이낸스코인",
      "summary": "2026년 4월 9일 기준, 바이낸스코인(BNB)은 글로벌 암호화폐 시장의 변동성 속에서도 바이낸스 생태계의 견고한 유틸리티를 바탕으로 안정적인 포지션을 유지하고 있습니다. 최근 시장은 규제 환경의 변화와 바이낸스 체인(BNB Chain)의 기술적 업그레이드 기대감이 교차하며 신중한 흐름을 보이고 있습니다. BNB는 거래소 수수료 할인 및 생태계 내 가스비 결제 수단으로서의 독보적인 위치를 점하고 있어 하방 경직성을 확보한 상태입니다. 향후 시장의 유동성 공급과 탈중앙화 금융(DeFi) 활성화 여부가 단기적인 가격 변동의 핵심 동인이 될 것으로 전망됩니다. 전반적으로 거시 경제의 불확실성 속에서도 생태계 확장 전략이 유효하게 작동하며 투자자들의 관심을 지속적으로 받고 있습니다.",
      "sentiment": "중립",
      "items": [
        {
          "title": "BNB Chain 생태계 확장 및 기술적 업그레이드",
          "type": "호재",
          "detail": "BNB Chain의 최신 네트워크 업그레이드는 트랜잭션 처리 속도를 기존 대비 약 20% 향상시키며 확장성을 크게 개선했습니다. 이러한 기술적 진보는 탈중앙화 애플리케이션(dApp) 개발자들의 유입을 촉진하여 BNB의 온체인 활동성을 높이는 핵심 요인으로 작용하고 있습니다. 네트워크 효율성 증대는 장기적으로 BNB의 가치 제고에 긍정적인 영향을 미칠 것이며, 특히 레이어 2 솔루션과의 연동 강화가 향후 가격 상승의 모멘텀이 될 것으로 분석됩니다."
        },
        {
          "title": "글로벌 규제 환경의 불확실성 지속",
          "type": "악재",
          "detail": "주요 경제권의 암호화폐 규제 강화 움직임은 바이낸스 거래소와 BNB의 시장 점유율에 잠재적인 리스크로 작용하고 있습니다. 특히 특정 국가에서의 라이선스 취득 지연이나 규제 당국의 조사 소식은 투자 심리를 위축시켜 단기적인 가격 조정의 빌미를 제공합니다. 규제 준수 비용의 증가는 거래소 수익성에 영향을 줄 수 있으며, 이는 BNB 소각 메커니즘의 효율성에도 간접적인 영향을 미칠 수 있어 지속적인 모니터링이 필요합니다."
        },
        {
          "title": "바이낸스 거래소의 시장 점유율 및 유동성 변화",
          "type": "중립",
          "detail": "바이낸스는 여전히 세계 최대 거래소로서 높은 유동성을 제공하고 있으나, 경쟁 거래소들의 공격적인 마케팅과 파생상품 시장 점유율 경쟁이 심화되고 있습니다. 현재 BNB의 거래량은 시장 전체 흐름과 밀접하게 연동되어 있으며, 거래소 내 BNB 보유량과 스테이킹 물량은 안정적인 수준을 유지하고 있습니다. 향후 거래소의 시장 점유율이 50% 이상을 견고히 유지할 경우 BNB의 가격 방어력은 더욱 강화될 것이나, 점유율 하락 시에는 가격 변동성이 확대될 가능성이 큽니다."
        }
      ]
    },
    {
      "id": "solana",
      "name": "솔라나",
      "summary": "2026년 4월 9일 기준, 솔라나(SOL)는 고성능 블록체인으로서의 입지를 공고히 하며 탈중앙화 금융(DeFi) 및 NFT 생태계의 활발한 활동을 바탕으로 시장의 주목을 받고 있습니다. 최근 네트워크 처리 속도 개선과 확장성 솔루션의 성공적인 안착으로 기관 투자자들의 관심이 지속되고 있으며, 이는 솔라나의 가격 방어력에 긍정적인 영향을 미치고 있습니다. 다만, 거시 경제의 불확실성과 암호화폐 시장 전반의 변동성 확대는 단기적인 가격 조정의 리스크로 작용할 수 있습니다. 전반적으로 솔라나는 기술적 우위를 바탕으로 시장 점유율을 확대하고 있으나, 네트워크 안정성 및 보안에 대한 지속적인 검증이 향후 성장의 핵심 변수가 될 것으로 전망됩니다.",
      "sentiment": "긍정",
      "items": [
        {
          "title": "네트워크 처리량 및 확장성 업그레이드 성과",
          "type": "호재",
          "detail": "솔라나 네트워크의 최신 업그레이드를 통해 초당 트랜잭션 처리량(TPS)이 이전 대비 15% 향상되었으며, 이는 대규모 온체인 활동을 지원하는 핵심 동력이 되고 있습니다. 이러한 기술적 개선은 네트워크 수수료를 안정화하고 사용자 경험을 개선하여, 경쟁 블록체인 대비 우월한 경쟁력을 확보하는 데 기여하고 있습니다. 향후 더 많은 기업형 애플리케이션이 솔라나 기반으로 구축될 가능성을 높여 장기적인 생태계 가치 상승을 견인할 것으로 분석됩니다."
        },
        {
          "title": "기관 투자자 유입 및 DeFi TVL 증가",
          "type": "호재",
          "detail": "최근 솔라나 생태계 내 탈중앙화 금융(DeFi)의 총 예치 자산(TVL)이 전 분기 대비 12% 증가하며 강력한 자본 유입을 증명하고 있습니다. 특히 기관 투자자들을 대상으로 한 스테이킹 서비스와 파생상품 시장의 활성화가 가격 상승의 주요 동력으로 작용하고 있습니다. 이러한 자본의 유입은 솔라나의 시장 신뢰도를 높이며, 향후 시장 변동성 상황에서도 가격 하방 경직성을 확보하는 데 긍정적인 역할을 할 것으로 보입니다."
        },
        {
          "title": "거시 경제 불확실성에 따른 시장 변동성 확대",
          "type": "악재",
          "detail": "글로벌 금리 정책의 불확실성과 인플레이션 우려가 지속되면서 암호화폐 시장 전반에 걸친 투자 심리가 위축되고 있습니다. 솔라나 역시 이러한 매크로 환경의 영향에서 자유롭지 못하며, 단기적으로는 기술적 호재에도 불구하고 시장 전체의 매도세에 동조화될 가능성이 존재합니다. 투자자들은 향후 발표될 주요 경제 지표에 따라 솔라나의 단기 가격 변동성이 크게 확대될 수 있음을 유의해야 하며, 리스크 관리가 필요한 시점입니다."
        }
      ]
    },
    {
      "id": "ripple",
      "name": "리플",
      "summary": "2026년 4월 현재 리플(XRP)은 글로벌 결제 네트워크로서의 입지를 공고히 하며 기관 투자자들의 지속적인 관심을 받고 있습니다. 최근 시장은 리플의 국경 간 결제 솔루션 채택 확대와 규제 환경의 명확성에 주목하고 있으며, 이는 XRP 가격의 변동성을 결정짓는 핵심 요인으로 작용하고 있습니다. 전반적인 암호화폐 시장의 회복세와 맞물려 리플은 기술적 지지선을 테스트하며 완만한 상승 모멘텀을 형성하려는 움직임을 보입니다. 다만, 거시 경제의 불확실성과 여전히 잔존하는 규제 리스크가 투자 심리에 영향을 미치고 있어 신중한 접근이 요구되는 시점입니다.",
      "sentiment": "중립",
      "items": [
        {
          "title": "글로벌 금융기관의 리플 결제 솔루션 채택 확대",
          "type": "호재",
          "detail": "최근 다수의 아시아 및 유럽 금융기관이 리플의 ODL(On-Demand Liquidity) 서비스를 도입하며 실제 거래량이 전 분기 대비 약 15% 증가하는 성과를 보였습니다. 이는 XRP의 실사용 사례를 증명함으로써 자산 가치에 대한 근본적인 신뢰를 높이는 계기가 되고 있습니다. 이러한 기관 채택의 증가는 향후 XRP의 유동성을 강화하고 장기적인 가격 상승을 견인할 강력한 펀더멘털로 작용할 전망입니다."
        },
        {
          "title": "미국 내 암호화폐 규제 프레임워크의 불확실성 지속",
          "type": "악재",
          "detail": "미국 금융 당국의 디지털 자산 분류에 대한 최종 가이드라인이 지연되면서 리플을 포함한 주요 알트코인 시장의 투자 심리가 위축되고 있습니다. 특히 특정 거래소에서의 XRP 거래 제한 가능성에 대한 루머가 시장의 변동성을 5~8%가량 확대시키는 요인이 되고 있습니다. 규제 불확실성이 해소되기 전까지는 기관 투자자들이 대규모 자금 유입을 주저할 가능성이 높아 단기적인 가격 횡보세가 이어질 것으로 예상됩니다."
        },
        {
          "title": "XRP 레저(XRPL) 생태계 확장 및 스마트 컨트랙트 기능 강화",
          "type": "호재",
          "detail": "리플은 최근 XRPL의 사이드체인 기능을 강화하여 탈중앙화 금융(DeFi) 및 NFT 프로젝트 유치를 가속화하고 있습니다. 개발자 활동 지수가 지난달 대비 12% 상승하며 생태계 활성도가 높아지고 있으며, 이는 네트워크 가치 상승으로 직결될 가능성이 큽니다. 기술적 고도화가 성공적으로 안착할 경우, 단순 결제 수단을 넘어선 플랫폼으로서의 가치가 재평가받으며 XRP 가격의 추가적인 상승 동력을 제공할 것입니다."
        }
      ]
    },
    {
      "id": "cardano",
      "name": "에이다",
      "summary": "에이다(Cardano)는 2026년 4월 현재, 네트워크의 탈중앙화 거버넌스 완성 이후 생태계 확장성과 처리 속도 개선에 집중하며 시장 내 입지를 다지고 있습니다. 최근 시장 전반의 변동성 속에서도 카르다노는 강력한 커뮤니티 지지와 기술적 안정성을 바탕으로 주요 레이어 1 프로젝트로서의 포지션을 유지하고 있습니다. 다만, 경쟁 스마트 컨트랙트 플랫폼들과의 치열한 점유율 경쟁과 기관 투자자들의 자금 유입 속도가 기대에 미치지 못하면서 가격은 횡보세를 보이고 있습니다. 향후 온체인 데이터의 활성화와 대규모 디앱(dApp) 유입 여부가 단기적인 가격 모멘텀을 결정할 핵심 변수가 될 것입니다.",
      "sentiment": "중립",
      "items": [
        {
          "title": "네트워크 업그레이드 및 처리량 최적화",
          "type": "호재",
          "detail": "최근 카르다노는 네트워크 처리량(TPS)을 대폭 개선하는 프로토콜 업데이트를 성공적으로 완료하며 확장성 문제를 해결하고 있습니다. 이번 업데이트로 인해 트랜잭션 수수료가 이전 대비 약 15% 감소하여 사용자 경험이 크게 개선되었습니다. 이러한 기술적 진보는 향후 더 많은 디앱 개발자들을 생태계로 유인하여 온체인 활동량을 증가시킬 것으로 전망되며, 장기적인 가격 상승의 견고한 기반이 될 것입니다."
        },
        {
          "title": "레이어 1 경쟁 심화 및 시장 점유율 정체",
          "type": "악재",
          "detail": "이더리움 및 솔라나 등 경쟁 레이어 1 프로젝트들이 공격적인 마케팅과 생태계 보조금 정책을 펼치면서 카르다노의 총 예치 자산(TVL) 증가세가 다소 둔화되었습니다. 현재 카르다노의 TVL은 전 분기 대비 약 5% 수준의 완만한 성장에 그치고 있어, 시장 점유율 확대에 어려움을 겪고 있습니다. 기관 투자자들은 더 높은 수익률을 제공하는 신규 체인으로 자금을 분산하고 있어, 카르다노가 차별화된 유틸리티를 증명하지 못할 경우 단기적인 가격 압박이 지속될 수 있습니다."
        },
        {
          "title": "거버넌스 모델의 실효성 검증 단계 진입",
          "type": "중립",
          "detail": "카르다노의 핵심인 볼테르(Voltaire) 시대의 탈중앙화 거버넌스가 본격적으로 가동되면서 의사결정 과정의 투명성은 높아졌으나, 정책 결정 속도가 느려질 수 있다는 우려가 제기되고 있습니다. 커뮤니티 투표를 통한 자금 배분 효율성이 향후 6개월 내에 입증되어야 하며, 이는 프로젝트의 신뢰도에 직접적인 영향을 미칠 것입니다. 거버넌스 체계가 효율적으로 작동한다면 장기적인 투자 매력도가 상승하겠지만, 의사결정 지연이 발생할 경우 투자 심리에 부정적인 영향을 줄 가능성이 있습니다."
        }
      ]
    },
    {
      "id": "dogecoin",
      "name": "도지코인",
      "summary": "2026년 4월 9일 기준 도지코인은 전반적인 암호화폐 시장의 변동성 속에서 밈코인 특유의 높은 투기적 수요와 커뮤니티 기반의 지지력을 유지하고 있습니다. 최근 시장은 주요 거시경제 지표 발표를 앞두고 관망세를 보이고 있으며, 도지코인 역시 기술적 지지선과 저항선 사이에서 횡보하는 모습을 나타냅니다. 일론 머스크의 발언이나 X(구 트위터) 플랫폼 내 결제 기능 도입 가능성에 대한 기대감이 여전히 가격의 하방 경직성을 확보하는 핵심 요인으로 작용하고 있습니다. 다만, 유틸리티 확장성 부족에 대한 시장의 근본적인 의구심은 여전히 상단 돌파를 제한하는 요소입니다. 향후 도지코인은 기술적 모멘텀보다는 생태계 내 실질적인 활용처 확대 여부에 따라 방향성이 결정될 것으로 전망됩니다.",
      "sentiment": "중립",
      "items": [
        {
          "title": "X(구 트위터) 결제 시스템 통합 기대감 지속",
          "type": "호재",
          "detail": "일론 머스크가 추진 중인 X 플랫폼 내 결제 서비스에 도지코인이 포함될 것이라는 시장의 기대감은 여전히 강력한 지지 요인입니다. 만약 공식적으로 결제 수단으로 채택될 경우, 도지코인의 일일 거래량은 현재 대비 최소 30~50% 이상 급증할 가능성이 있습니다. 다만, 구체적인 타임라인이 부재한 상황이므로 실질적인 발표 전까지는 기대감에 의한 단기 변동성 확대에 유의해야 합니다."
        },
        {
          "title": "밈코인 섹터 내 경쟁 심화 및 자금 분산",
          "type": "악재",
          "detail": "최근 시장에서 시바이누, 페페 등 신규 밈코인들이 강력한 커뮤니티와 생태계 확장성을 앞세워 도지코인의 시장 점유율을 잠식하고 있습니다. 이러한 자금 분산 현상은 도지코인의 시가총액 비중을 약화시키며, 상승장에서의 탄력성을 떨어뜨리는 결과를 초래하고 있습니다. 투자자들의 관심이 분산됨에 따라 도지코인이 과거와 같은 폭발적인 상승률을 기록하기 위해서는 차별화된 유틸리티 확보가 시급한 과제입니다."
        },
        {
          "title": "거시경제 불확실성에 따른 위험자산 회피 심리",
          "type": "중립",
          "detail": "글로벌 금리 정책의 불확실성이 지속되면서 암호화폐와 같은 위험자산 전반에 대한 투자 심리가 위축되고 있습니다. 도지코인은 특히 시장 하락기에는 비트코인보다 높은 베타(Beta) 값을 보이며 하락폭이 커지는 경향이 있어, 거시경제 지표 악화 시 단기적인 가격 조정 압력이 강해질 수 있습니다. 현재 0.15달러~0.20달러 구간에서의 횡보세가 길어질수록 투자자들의 피로감이 누적되어 매도세가 강화될 위험이 존재합니다."
        }
      ]
    },
    {
      "id": "avalanche-2",
      "name": "아발란체",
      "summary": "아발란체(AVAX)는 2026년 4월 현재, 고성능 레이어 1 블록체인으로서의 기술적 우위를 바탕으로 기관 투자자들의 지속적인 관심을 받고 있습니다. 최근 네트워크 업그레이드를 통해 처리 속도와 확장성이 개선되면서 탈중앙화 금융(DeFi) 및 실물 자산(RWA) 토큰화 분야에서 선도적인 입지를 굳히고 있습니다. 다만, 전반적인 암호화폐 시장의 변동성 확대와 경쟁 레이어 1 프로젝트들과의 점유율 경쟁이 심화되면서 단기적인 가격 조정 압력을 받고 있는 상황입니다. 투자자들은 네트워크 내 총 예치 자산(TVL)의 추이와 주요 파트너십의 실질적인 성과를 면밀히 주시하며 신중한 접근을 취하고 있습니다.",
      "sentiment": "중립",
      "items": [
        {
          "title": "RWA 토큰화 플랫폼 확장 및 기관 파트너십 강화",
          "type": "호재",
          "detail": "아발란체는 최근 글로벌 금융 기관들과 협력하여 실물 자산(RWA) 토큰화 프로젝트를 성공적으로 확장하고 있습니다. 특히 서브넷 기술을 활용한 기업용 블록체인 솔루션 도입이 증가하며, 네트워크 내 RWA 관련 거래량이 전 분기 대비 약 15% 증가하는 성과를 보였습니다. 이러한 기관 중심의 생태계 확장은 AVAX의 장기적인 내재 가치를 높이고, 단순 투기성 자산을 넘어 실질적인 유틸리티 토큰으로서의 입지를 강화하는 핵심 동력이 될 것으로 전망됩니다."
        },
        {
          "title": "경쟁 레이어 1 프로젝트와의 점유율 경쟁 심화",
          "type": "악재",
          "detail": "솔라나(Solana) 및 이더리움 레이어 2 솔루션들과의 시장 점유율 경쟁이 더욱 치열해지면서 아발란체의 신규 사용자 유입 속도가 다소 둔화되는 양상을 보이고 있습니다. 최근 데이터에 따르면 일일 활성 주소(DAA) 수가 지난달 대비 약 8% 감소하며 네트워크 활동성이 정체된 모습을 나타냈습니다. 이는 단기적으로 가격 상승을 제한하는 요인으로 작용할 수 있으며, 향후 시장 지배력을 유지하기 위해서는 차별화된 킬러 앱(dApp) 확보가 시급한 과제로 평가됩니다."
        },
        {
          "title": "네트워크 업그레이드 및 기술적 확장성 개선",
          "type": "호재",
          "detail": "최근 완료된 아발란체 네트워크의 최신 업그레이드는 트랜잭션 처리 효율을 극대화하여 가스비를 약 12% 절감하는 효과를 가져왔습니다. 이러한 기술적 개선은 개발자 친화적인 환경을 조성하여 생태계 내 신규 프로젝트 유입을 촉진할 것으로 기대됩니다. 기술적 안정성이 확보됨에 따라 네트워크의 신뢰도가 상승하고 있으며, 이는 향후 시장 반등 시 강력한 기술적 기반으로 작용하여 가격 회복 탄력성을 높이는 데 기여할 것입니다."
        }
      ]
    },
    {
      "id": "chainlink",
      "name": "체인링크",
      "summary": "체인링크(LINK)는 2026년 4월 현재, 탈중앙화 오라클 네트워크의 표준으로서 RWA(실물자산) 토큰화 시장의 급격한 성장에 힘입어 견고한 시장 지위를 유지하고 있습니다. 최근 금융 기관들의 블록체인 도입이 가속화되면서 CCIP(Cross-Chain Interoperability Protocol)를 활용한 기관급 솔루션 수요가 증가하고 있으며, 이는 네트워크 가치 상승의 핵심 동력으로 작용 중입니다. 다만, 전반적인 암호화폐 시장의 변동성과 거시 경제적 불확실성으로 인해 단기적인 가격 조정 압력 또한 공존하고 있는 상황입니다. 기술적 지표상으로는 주요 저항선 돌파 여부가 향후 추세를 결정할 핵심 변수가 될 것으로 보입니다. 전반적으로 체인링크는 인프라 중심의 강력한 펀더멘털을 바탕으로 중장기적 성장 잠재력을 높게 평가받고 있습니다.",
      "sentiment": "긍정",
      "items": [
        {
          "title": "RWA 토큰화 시장 내 CCIP 채택 확대",
          "type": "호재",
          "detail": "글로벌 금융 기관들이 자산 토큰화를 위해 체인링크의 CCIP를 표준 프로토콜로 채택하는 사례가 지속적으로 증가하고 있습니다. 이는 네트워크의 실제 사용량(Usage)을 직접적으로 견인하며, LINK 토큰의 유틸리티 가치를 강화하는 핵심 요소입니다. 분석에 따르면, RWA 관련 트랜잭션 처리량이 전 분기 대비 약 15% 이상 증가하며 네트워크 수익성에 긍정적인 신호를 보내고 있습니다. 향후 기관 자금 유입이 본격화될 경우, 이는 LINK의 장기적인 가격 상승을 뒷받침하는 강력한 모멘텀이 될 것입니다."
        },
        {
          "title": "네트워크 스테이킹 물량 증가 및 공급량 감소",
          "type": "호재",
          "detail": "체인링크 스테이킹 v0.2 및 후속 버전으로의 전환을 통해 유통 공급량 중 상당 부분이 락업(Lock-up) 상태로 유지되고 있습니다. 현재 전체 공급량의 약 25% 이상이 스테이킹에 참여하고 있어, 시장 내 매도 압력을 효과적으로 완화하고 있습니다. 이러한 공급 제한 효과는 매수세가 유입될 때 가격 탄력성을 높이는 역할을 합니다. 향후 스테이킹 보상 구조의 최적화가 지속된다면, 장기 보유자들의 이탈을 방지하고 가격 안정성을 더욱 공고히 할 것으로 전망됩니다."
        },
        {
          "title": "거시 경제 불확실성에 따른 시장 변동성",
          "type": "악재",
          "detail": "2026년 4월 현재, 글로벌 금리 정책의 불확실성과 지정학적 리스크가 암호화폐 시장 전반의 투자 심리를 위축시키고 있습니다. 체인링크는 펀더멘털이 우수함에도 불구하고, 비트코인 및 이더리움과의 높은 상관관계로 인해 시장 하락기에는 동반 하락하는 경향을 보입니다. 단기적으로는 주요 지지선인 15~18달러 구간의 방어 여부가 중요하며, 시장 전체의 위험 회피 심리가 지속될 경우 일시적인 가격 조정이 불가피할 수 있습니다. 투자자들은 거시 경제 지표 발표에 따른 변동성 확대에 유의해야 합니다."
        }
      ]
    },
    {
      "id": "polkadot",
      "name": "폴카닷",
      "summary": "폴카닷(DOT)은 2026년 4월 현재, 생태계의 기술적 고도화와 거버넌스 개편을 통해 네트워크 효율성을 극대화하는 데 집중하고 있습니다. 최근 시장 전반의 변동성 속에서도 폴카닷은 파라체인 확장성과 상호운용성이라는 고유의 강점을 바탕으로 기관 투자자들의 관심을 유지하고 있습니다. 다만, 경쟁 레이어1 프로젝트들과의 점유율 경쟁이 심화되면서 네트워크 활성도와 TVL(총 예치 자산) 성장을 증명해야 하는 과제에 직면해 있습니다. 전반적으로 기술적 로드맵은 순항 중이나, 단기적으로는 거시 경제 지표와 연동된 가격 변동성을 보일 것으로 예상됩니다. 투자자들은 향후 주요 파트너십 발표와 네트워크 업그레이드에 따른 실질적인 온체인 데이터 변화를 면밀히 주시해야 합니다.",
      "sentiment": "중립",
      "items": [
        {
          "title": "폴카닷 2.0 업그레이드 및 거버넌스 효율화",
          "type": "호재",
          "detail": "폴카닷 2.0으로의 전환은 기존의 경직된 슬롯 경매 방식을 탈피하여 유연한 블록스페이스 할당 모델을 도입함으로써 네트워크 효율성을 크게 개선하고 있습니다. 이러한 변화는 개발자들의 진입 장벽을 낮추어 생태계 내 신규 프로젝트 유입을 가속화할 것으로 기대됩니다. 데이터에 따르면 업그레이드 이후 네트워크 처리 속도와 비용 효율성이 이전 대비 약 20% 이상 개선된 것으로 나타나, 장기적인 가격 상승의 기술적 기반이 될 것입니다."
        },
        {
          "title": "경쟁 레이어1 프로젝트와의 점유율 경쟁 심화",
          "type": "악재",
          "detail": "이더리움 레이어2 솔루션 및 기타 고성능 레이어1 블록체인들이 시장 점유율을 빠르게 확대하면서 폴카닷의 고유 가치 제안이 희석되고 있다는 우려가 존재합니다. 최근 온체인 데이터상 활성 주소 수와 일일 거래량이 경쟁사 대비 정체된 모습을 보이며 투자 심리에 부정적인 영향을 미치고 있습니다. 이러한 경쟁 구도에서 우위를 점하기 위해서는 단순한 기술적 우위를 넘어, 실질적인 대규모 디앱(dApp) 유치와 사용자 기반 확장이 시급한 상황입니다."
        },
        {
          "title": "기관 투자자들의 스테이킹 수요 증가",
          "type": "호재",
          "detail": "최근 폴카닷 네트워크의 스테이킹 참여율이 전체 공급량의 50%를 상회하며 네트워크 보안성과 안정성에 대한 신뢰가 강화되고 있습니다. 특히 기관 투자자들을 중심으로 한 장기 보유 물량이 증가하면서 시장의 매도 압력이 완화되는 효과를 보이고 있습니다. 이는 향후 시장 반등 시 가격 탄력성을 높이는 요인으로 작용할 수 있으며, 스테이킹 보상 모델의 안정성이 투자자들에게 매력적인 수익원으로 인식되고 있습니다."
        }
      ]
    }
  ]
}