{
  "date": "2026-03-31",
  "generatedAt": "2026-03-30T16:54:44.760Z",
  "data": [
    {
      "symbol": "005930",
      "name": "삼성전자",
      "sector": "반도체",
      "price": 176300,
      "change": -1.89,
      "volume": "0",
      "marketCap": "-"
    },
    {
      "symbol": "000660",
      "name": "SK하이닉스",
      "sector": "반도체",
      "price": 873000,
      "change": -5.31,
      "volume": "0",
      "marketCap": "-"
    },
    {
      "symbol": "373220",
      "name": "LG에너지솔루션",
      "sector": "2차전지",
      "price": 410000,
      "change": 3.93,
      "volume": "0",
      "marketCap": "-"
    },
    {
      "symbol": "207940",
      "name": "삼성바이오로직스",
      "sector": "바이오",
      "price": 1530000,
      "change": -4.73,
      "volume": "0",
      "marketCap": "-"
    },
    {
      "symbol": "005380",
      "name": "현대차",
      "sector": "자동차",
      "price": 469500,
      "change": -5.15,
      "volume": "0",
      "marketCap": "-"
    },
    {
      "symbol": "006400",
      "name": "삼성SDI",
      "sector": "2차전지",
      "price": 412500,
      "change": 1.73,
      "volume": "0",
      "marketCap": "-"
    },
    {
      "symbol": "051910",
      "name": "LG화학",
      "sector": "화학",
      "price": 322000,
      "change": 2.88,
      "volume": "0",
      "marketCap": "-"
    },
    {
      "symbol": "035420",
      "name": "NAVER",
      "sector": "IT",
      "price": 207000,
      "change": -2.59,
      "volume": "0",
      "marketCap": "-"
    },
    {
      "symbol": "035720",
      "name": "카카오",
      "sector": "IT",
      "price": 47100,
      "change": -3.48,
      "volume": "0",
      "marketCap": "-"
    },
    {
      "symbol": "068270",
      "name": "셀트리온",
      "sector": "바이오",
      "price": 201500,
      "change": -2.18,
      "volume": "0",
      "marketCap": "-"
    }
  ]
}