{
  "date": "2026-05-13",
  "generatedAt": "2026-05-12T17:59:17.008Z",
  "data": {
    "title": "2026년 5월 2주차 신한금융그룹 위클리 리포트",
    "summary": {
      "title": "북중미 IR 및 밸류업 가속",
      "body": "진옥동 회장이 북중미 지역에서 '신한 밸류업 2.0' 전략을 공유하며 글로벌 투자자 소통을 강화하고 있습니다. 1분기 사상 최대 실적 달성과 함께 ROE 및 주주환원 체계의 구체화로 시장 신뢰를 확보 중입니다. 다만, 중동 지정학적 리스크에 따른 시장 변동성 확대는 주의가 필요합니다.",
      "mood": "positive",
      "stockPrice": "96,700원",
      "stockChange": "-0.51%",
      "stockIsUp": false
    },
    "holdingIssues": [
      {
        "category": "IR/ESG",
        "title": "진옥동 회장 북중미 IR 순방",
        "body": "진옥동 신한금융그룹 회장이 5월 10일부터 22일까지 미국, 멕시코, 캐나다를 방문하여 해외 기관투자자 대상 투자설명회(IR)를 진행하고 있습니다. 이번 순방은 지난달 발표한 '신한 밸류업 2.0' 전략을 글로벌 시장에 직접 알리고, 그룹의 중장기 기업가치 제고 계획을 공유하기 위해 마련되었습니다. 진 회장은 ROE와 성장률에 연동된 주주환원 체계와 자본정책의 예측 가능성을 강조하며 시장 접점을 확대하고 있습니다. 또한 현지 법인과 지점을 방문하여 글로벌 사업 운영 현황을 점검하고, 중동 전쟁 장기화 등 글로벌 금융시장 변동성에 대한 대응 방안을 논의하며 시장 신뢰를 다지고 있습니다.",
        "importance": "high"
      },
      {
        "category": "실적",
        "title": "1분기 사상 최대 실적 달성",
        "body": "신한지주는 2026년 1분기 연결순이익 1.62조 원을 기록하며 분기 기준 사상 최대 실적을 달성했습니다. 이는 전년 동기 대비 약 9% 증가한 수치로, 이자이익과 비이자이익이 동반 성장하며 견조한 이익 체력을 입증했습니다. 특히 수수료 이익의 큰 폭 증가가 실적 개선을 주도하며 비은행 부문의 경쟁력이 강화되고 있음을 보여주었습니다. 이러한 실적 호조는 단순한 일회성 요인이 아닌 구조적인 수익성 개선으로 평가받고 있으며, 향후 연간 실적 전망치 상향의 근거가 되고 있습니다.",
        "importance": "high"
      }
    ],
    "subsidiaryUpdates": [
      {
        "company": "신한은행",
        "icon": "account_balance",
        "color": "blue",
        "headline": "디지털 및 글로벌 협력 강화",
        "details": [
          "고려대학교 기술지주와 업무협약을 체결하여 기술 금융 지원 확대",
          "어린이날 맞이 '무럭무럭 성장 프로젝트' 추진 등 사회공헌 강화",
          "수출입 아카데미 개최를 통한 기업 고객 대상 맞춤형 금융 서비스 제공"
        ],
        "sentiment": "positive"
      },
      {
        "company": "신한카드",
        "icon": "credit_card",
        "color": "red",
        "headline": "수익성 개선 및 리스크 관리",
        "details": [
          "희망퇴직 실시를 통한 조직 효율화 및 비용 절감 추진",
          "고금리 장기화에 따른 취약 차주 중심의 건전성 관리 강화",
          "비은행 부문 이익 기여도 확대를 위한 포트폴리오 재편"
        ],
        "sentiment": "neutral"
      },
      {
        "company": "신한투자증권",
        "icon": "show_chart",
        "color": "green",
        "headline": "개인 투자자 데이터 분석 및 서비스",
        "details": [
          "2026년 1분기 개인 투자자 국내 주식 투자 성과 분석 리포트 발간",
          "미성년자 및 부모 고객 대상 계좌 개설 트렌드 분석 서비스 제공",
          "증권형 토큰(STO) 플랫폼 구축을 위한 민간 협의체 주도"
        ],
        "sentiment": "positive"
      },
      {
        "company": "신한라이프",
        "icon": "favorite",
        "color": "pink",
        "headline": "소비자 보호 및 브랜드 캠페인",
        "details": [
          "완전판매 문화 확산을 위한 '소비자보호의 날' 정례 운영",
          "고객 참여형 '신그러운 라이프 챌린지' 전개로 브랜드 친밀도 제고",
          "보험업 부진 기조 속 상품 포트폴리오 최적화 노력"
        ],
        "sentiment": "neutral"
      },
      {
        "company": "신한캐피탈",
        "icon": "directions_car",
        "color": "orange",
        "headline": "투자 자산 효율화 및 성장",
        "details": [
          "그룹 내 비은행 부문 수익성 제고를 위한 자산 리밸런싱",
          "기업 금융 중심의 대출 포트폴리오 다변화 전략 추진",
          "시장 변동성 대응을 위한 보수적 리스크 관리 기조 유지"
        ],
        "sentiment": "positive"
      }
    ],
    "keyMetrics": [
      {
        "label": "신한지주 시가총액",
        "value": "45조 8,990억 원",
        "change": "-0.51%"
      },
      {
        "label": "신한은행 NIM",
        "value": "1.93% (예상)",
        "change": "+3bp (YoY)"
      },
      {
        "label": "그룹 ROE",
        "value": "10~12% (목표)",
        "change": "상향 기조"
      }
    ],
    "analystView": {
      "consensus": "매수",
      "targetPrice": "120,000원",
      "currentPrice": "96,700원",
      "upside": "24.1%",
      "comment": "신한지주는 사상 최대 실적과 구체적인 밸류업 정책을 통해 자본 효율성을 입증하고 있습니다. ROE와 성장률에 연동된 주주환원 공식은 시장의 신뢰를 높이는 핵심 요소입니다. 중동 리스크 등 대외 변수가 존재하나, 구조적 이익 체력 강화와 주주환원 의지를 고려할 때 매수 관점을 유지합니다."
    },
    "globalPeerComparison": [
      {
        "name": "KB금융",
        "change": "-1.79%",
        "isUp": false,
        "note": "CET1 비율 소폭 하락 및 시장 변동성 영향"
      },
      {
        "name": "하나금융",
        "change": "-1.79%",
        "isUp": false,
        "note": "자본 비율 관리 및 업종 전반 하락세 동조"
      },
      {
        "name": "우리금융",
        "change": "-1.05%",
        "isUp": false,
        "note": "자산 리밸런싱 노력에도 불구하고 시장 조정 영향"
      }
    ],
    "riskFactors": [
      {
        "factor": "지정학적 리스크",
        "description": "중동 전쟁 장기화에 따른 글로벌 금융시장 변동성 확대 및 부실 압력 증가",
        "level": "high"
      },
      {
        "factor": "자본 규제",
        "description": "고금리 장기화로 인한 CET1 비율 하락 압박 및 규제 준수 부담",
        "level": "medium"
      }
    ],
    "nextWeek": {
      "preview": "다음 주는 진옥동 회장의 북중미 IR 성과가 구체화되면서 글로벌 투자자들의 반응이 주가에 반영될 것으로 보입니다. 국내외 금융시장 변동성 속에서도 1분기 실적 모멘텀이 이어질지 주목됩니다. 특히 정부의 밸류업 정책 관련 추가적인 세부 지침이나 금융당국의 자본 규제 합리화 논의가 주가 변동성을 키울 수 있습니다. 보수적인 리스크 관리 기조 속에서도 주주환원 정책에 대한 시장의 기대감이 주가 하단을 지지할 것으로 전망됩니다.",
      "events": [
        {
          "date": "2026-05-18",
          "day": "월",
          "event": "진옥동 회장 북중미 IR 순방 지속"
        },
        {
          "date": "2026-05-20",
          "day": "수",
          "event": "금융권 주요 경영진 리스크 관리 회의"
        }
      ]
    }
  }
}